Workbook
Name CenaSE: INDIRECT([2]OUTPUT_SIP!$AH$13)
Name EDV: INDIRECT([2]OUTPUT_SIP!$AH$8)
Name inflacija: [2]parametri!$B$5
Name LastnaRaba: INDIRECT([2]OUTPUT_SIP!$AH$10)
Name PowerSE: INDIRECT([2]OUTPUT_SIP!$AH$7)
Name ProizvodnjaSE: INDIRECT([2]OUTPUT_SIP!$AH$9)
Name Samooskrbnost: INDIRECT([2]OUTPUT_SIP!$AH$12)
Name Viski: INDIRECT([2]OUTPUT_SIP!$AH$11)

Sheet Življenska doba JEK2
A1: Življenska doba [let] | B1: Delež pojavljanja [%]
A2: 40 | B2: 0
A3: 60 | B3: 0.2
A4: 80 | B4: 0.6
A5: 100 | B5: 0.2

Sheet Inštalirana kapaciteta
A1: Inštalirana kapaciteta [MW] | B1: 1000
B2: 1250
B3: 1650

Sheet Capacity factor
A1: Trikotna distribucija
A2: Min | B2: 0.85
A3: Modus | B3: 0.91
A4: Max | B4: 0.95
A5: Povperčen CF | B5: =AVERAGE(B2:B4) -> 0.90333333
L7: Chooz B-2 | M7: Generation II (Upgraded in the 1980s,1990s and 2000s after Chernobyl) | O7: PWR (N4 REP 1450) | P7: 1500 | Q7: 69.6 | R7: =IF(Q7>75,Q7,"")
L8: Chooz B-1 | M8: Generation II (Upgraded in the 1980s,1990s and 2000s after Chernobyl) | O8: PWR (N4 REP 1450) | P8: 1500 | Q8: 71.6 | R8: =IF(Q8>75,Q8,"")
L9: Golfech-2 | M9: Generation II (Upgraded in the 1980s,1990s and 2000s after Chernobyl) | O9: PWR (P4 REP 1300) | P9: 1310 | Q9: 74.4 | R9: =IF(Q9>75,Q9,"")
L10: Penly-2 | M10: Generation II (Upgraded in the 1980s,1990s and 2000s after Chernobyl) | O10: PWR (P4 REP 1300) | P10: 1330 | Q10: 75.1 | R10: =IF(Q10>75,Q10,"") -> 75.1
L11: Cattenom-4 | M11: Generation II (Upgraded in the 1980s,1990s and 2000s after Chernobyl) | O11: PWR (P4 REP 1300) | P11: 1300 | Q11: 75.5 | R11: =IF(Q11>75,Q11,"") -> 75.5
L12: Cattenom-3 | M12: Generation II (Upgraded in the 1980s,1990s and 2000s after Chernobyl) | O12: PWR (P4 REP 1300) | P12: 1300 | Q12: 71.3 | R12: =IF(Q12>75,Q12,"")
L13: Golfech-1 | M13: Generation II (Upgraded in the 1980s,1990s and 2000s after Chernobyl) | O13: PWR (P4 REP 1300) | P13: 1310 | Q13: 72.5 | R13: =IF(Q13>75,Q13,"")
L14: Penly-2 | M14: Generation II (Upgraded in the 1980s,1990s and 2000s after Chernobyl) | O14: PWR (P4 REP 1300) | P14: 1330 | Q14: 72.3 | R14: =IF(Q14>75,Q14,"")
L15: Nogent-2 | M15: Generation II (Upgraded in the 1980s,1990s and 2000s after Chernobyl) | O15: PWR (P4 REP 1300) | P15: 1310 | Q15: 74.2 | R15: =IF(Q15>75,Q15,"")
L16: Belleville-2 | M16: Generation II (Upgraded in the 1980s,1990s and 2000s after Chernobyl) | O16: PWR (P4 REP 1300) | P16: 1310 | Q16: 71.6 | R16: =IF(Q16>75,Q16,"")
L17: Chinon B-4 | M17: Generation II (Upgraded in the 1980s,1990s and 2000s after Chernobyl) | O17: PWR (CP2) | P17: 905 | Q17: 74.6 | R17: =IF(Q17>75,Q17,"")
L18: Nogent-1 | M18: Generation II (Upgraded in the 1980s,1990s and 2000s after Chernobyl) | O18: PWR (P4 REP 1300) | P18: 1310 | Q18: 72.4 | R18: =IF(Q18>75,Q18,"")
... L20: Cattenom-2 | M20: Generation II (Upgraded in the 1980s,1990s and 2000s after Chernobyl) | O20: PWR (P4 REP 1300) | P20: 1300 | Q20: 71.8 | R20: =IF(Q20>75,Q20,"")
L21: UK | R21: =IF(Q21>75,Q21,"")
L22: Bradwell 2 | M22: Generation III+ | O22: Hualong one | P22: 1150 | R22: =IF(Q22>75,Q22,"")
L23: Bradwell 1 | M23: Generation III+ | O23: Hualong one | P23: 1150 | R23: =IF(Q23>75,Q23,"")
L24: Sizewell C2 | M24: Generation III+ | O24: PWR (EPR-1600) | P24: 1670 | R24: =IF(Q24>75,Q24,"")
L25: Sizewell C1 | M25: Generation III+ | O25: PWR (EPR-1600) | P25: 1670 | R25: =IF(Q25>75,Q25,"")
L26: Hinkley Point C1 | M26: Generation III+ | O26: PWR (EPR-1600) | P26: 1630 | R26: =IF(Q26>75,Q26,"")
L27: Hinkley Point C2 | M27: Generation III+ | O27: PWR (EPR-1600) | P27: 1630 | R27: =IF(Q27>75,Q27,"")
L28: Sizewell B | M28: Generation II (Upgraded in the 1980s,1990s and 2000s after Chernobyl) | O28: PWR (SNUPPS) | P28: 1198 | Q28: 83.1 | R28: =IF(Q28>75,Q28,"") -> 83.1
L29: Torness-2 | M29: Generation II (Upgraded in the 1980s,1990s and 2000s after Chernobyl) | O29: GCR (AGR) | P29: 605 | Q29: 76.5 | R29: =IF(Q29>75,Q29,"") -> 76.5
L30: Heysham B-2 | M30: Generation II (Upgraded in the 1980s,1990s and 2000s after Chernobyl) | O30: GCR (AGR) | P30: 620 | Q30: 76.8 | R30: =IF(Q30>75,Q30,"") -> 76.8
L31: Heysham B-1 | M31: Generation II (Upgraded in the 1980s,1990s and 2000s after Chernobyl) | O31: GCR (AGR) | P31: 620 | Q31: 80.8 | R31: =IF(Q31>75,Q31,"") -> 80.8
L32: Torness-2 | M32: Generation II (Upgraded in the 1980s,1990s and 2000s after Chernobyl) | O32: GCR (AGR) | P32: 595 | Q32: 81.1 | R32: =IF(Q32>75,Q32,"") -> 81.1
L33: US | R33: =IF(Q33>75,Q33,"")
L34: Turkey point 7 | M34: Generation III+ | O34: PWR (AP-1000) | P34: 1538 | R34: =IF(Q34>75,Q34,"")
L35: Turkey point 6 | M35: Generation III+ | O35: PWR (AP-1000) | R35: =IF(Q35>75,Q35,"")
L36: Fermi 3 | M36: Generation III+ | O36: ESBWR | R36: =IF(Q36>75,Q36,"")
L37: North Anna | M37: Generation III+ | O37: ESBWR | R37: =IF(Q37>75,Q37,"")
L38: Clinch River | M38: Generation III+ | O38: / | R38: =IF(Q38>75,Q38,"")
L39: Bellefonte 2 | M39: Generation III+ | O39: PWR (B&W) | R39: =IF(Q39>75,Q39,"")
L40: Bellefonte 1 | M40: Generation III+ | O40: PWR (B&W) | R40: =IF(Q40>75,Q40,"")
L41: Salem 3 | M41: Generation III+ | O41: / | R41: =IF(Q41>75,Q41,"")
L42: Vogtle-4 | M42: Generation III+ | O42: PWR (AP1000) | P42: 1117 | R42: =IF(Q42>75,Q42,"")
L43: Vogtle-3 | M43: Generation III+ | O43: PWR (AP1000) | P43: 1117 | Q43: 99.3 | R43: =IF(Q43>75,Q43,"") -> 99.3
L44: Watts bar-2 | M44: Generation II (Upgraded in the 1980s,1990s and 2000s after Chernobyl) | O44: PWR (WH 4LP (ICECND)) | P44: 1164 | Q44: 80.4 | R44: =IF(Q44>75,Q44,"") -> 80.4
L45: Watts bar-1 | M45: Generation II (Upgraded in the 1980s,1990s and 2000s after Chernobyl) | O45: PWR (WH 4LP (ICECND)) | P45: 1157 | Q45: 89.9 | R45: =IF(Q45>75,Q45,"") -> 89.9
L46: Comanche peak-2 | M46: Generation II (Upgraded in the 1980s,1990s and 2000s after Chernobyl) | O46: PWR (WH 4LP (DRYAMB)) | P46: 1195 | Q46: 80.4 | R46: =IF(Q46>75,Q46,"") -> 80.4
L47: Seabrook-1 | M47: Generation II (Upgraded in the 1980s,1990s and 2000s after Chernobyl) | O47: PWR (WH 4LP (DRYAMB)) | P47: 1246 | Q47: 87.8 | R47: =IF(Q47>75,Q47,"") -> 87.8
L48: Comanche peak-1 | M48: Generation II (Upgraded in the 1980s,1990s and 2000s after Chernobyl) | O48: PWR (WH 4LP (DRYAMB)) | P48: 1205 | Q48: 88.6 | R48: =IF(Q48>75,Q48,"") -> 88.6
L49: Limerick-2 | M49: Generation II (Upgraded in the 1980s,1990s and 2000s after Chernobyl) | O49: BWR (BWR-4 (Mark 2)) | P49: 1134 | Q49: 93.4 | R49: =IF(Q49>75,Q49,"") -> 93.4
L50: South texas-2 | M50: Generation II (Upgraded in the 1980s,1990s and 2000s after Chernobyl) | O50: PWR (WH 4LP (DRYAMB)) | P50: 1280 | Q50: 85.6 | R50: =IF(Q50>75,Q50,"") -> 85.6
L51: Vogtle-2 | M51: Generation II (Upgraded in the 1980s,1990s and 2000s after Chernobyl) | O51: PWR (WH 4LP (DRYAMB)) | P51: 1152 | Q51: 92.1 | R51: =IF(Q51>75,Q51,"") -> 92.1
L52: Braidwood-2 | M52: Generation II (Upgraded in the 1980s,1990s and 2000s after Chernobyl) | O52: PWR (WH 4LP (DRYAMB)) | P52: 1160 | Q52: 91.4 | R52: =IF(Q52>75,Q52,"") -> 91.4
L53: South texas-1 | M53: Generation II (Upgraded in the 1980s,1990s and 2000s after Chernobyl) | O53: PWR (WH 4LP (DRYAMB)) | P53: 1280 | Q53: 85.8 | R53: =IF(Q53>75,Q53,"") -> 85.8
L54: Palo Verde-3 | M54: Generation II (Upgraded in the 1980s,1990s and 2000s after Chernobyl) | O54: PWR (CE80 2LP (DRYAMB)) | P54: 1312 | Q54: 86.3 | R54: =IF(Q54>75,Q54,"") -> 86.3
... L61: Harris-1 | M61: Generation II (Upgraded in the 1980s,1990s and 2000s after Chernobyl) | O61: PWR (WH 3LP (DRYAMB)) | P61: 964 | Q61: 89.9 | R61: =IF(Q61>75,Q61,"") -> 89.9
L62: SOUTH KOREA | R62: =IF(Q62>75,Q62,"")
L63: Shin Hanul 4 | M63: Generation III+ | O63: PWR (APR-1400) | P63: 1400 | R63: =IF(Q63>75,Q63,"")
L64: Shin Hanul 3 | M64: Generation III+ | O64: PWR (APR-1400) | P64: 1400 | R64: =IF(Q64>75,Q64,"")
L65: Shin Hanul 2 | M65: Generation III+ | O65: PWR (APR-1400) | P65: 1340 | R65: =IF(Q65>75,Q65,"")
L66: Shin Hanul 1 | M66: Generation III+ | O66: PWR (APR-1400) | P66: 1414 | Q66: 99.5 | R66: =IF(Q66>75,Q66,"") -> 99.5
L67: Saeul 2 | M67: Generation III+ | O67: PWR (APR-1400) | P67: 1418 | Q67: 83.9 | R67: =IF(Q67>75,Q67,"") -> 83.9
L68: Saeul 1 | M68: Generation III+ | O68: PWR (APR-1400) | P68: 1416 | Q68: 79.2 | R68: =IF(Q68>75,Q68,"") -> 79.2
L69: Shin Wolsong-2 | M69: Generation II (Upgraded in the 1980s,1990s and 2000s after Chernobyl) | O69: PWR (OPR-1000) | P69: 993 | Q69: 85.4 | R69: =IF(Q69>75,Q69,"") -> 85.4
L70: Shin Kori-2 | M70: Generation II (Upgraded in the 1980s,1990s and 2000s after Chernobyl) | O70: PWR (OPR-1000) | P70: 996 | Q70: 83.7 | R70: =IF(Q70>75,Q70,"") -> 83.7
L71: Shin Wolsong-1 | M71: Generation II (Upgraded in the 1980s,1990s and 2000s after Chernobyl) | O71: PWR (OPR-1000) | P71: 997 | Q71: 82.9 | R71: =IF(Q71>75,Q71,"") -> 82.9
L72: Shin Kori 1 | M72: Generation II (Upgraded in the 1980s,1990s and 2000s after Chernobyl) | O72: PWR (OPR-1000) | P72: 996 | Q72: 76.1 | R72: =IF(Q72>75,Q72,"") -> 76.1
L73: Hanul-6 | M73: Generation II (Upgraded in the 1980s,1990s and 2000s after Chernobyl) | O73: PWR (OPR-1000) | P73: 997 | Q73: 88.6 | R73: =IF(Q73>75,Q73,"") -> 88.6
L74: Hanul-5 | M74: Generation II (Upgraded in the 1980s,1990s and 2000s after Chernobyl) | O74: PWR (OPR-1000) | P74: 998 | Q74: 88.2 | R74: =IF(Q74>75,Q74,"") -> 88.2
L75: Hanbit-6 | M75: Generation II (Upgraded in the 1980s,1990s and 2000s after Chernobyl) | O75: PWR (OPR-1000) | P75: 993 | Q75: 85.1 | R75: =IF(Q75>75,Q75,"") -> 85.1
L76: Hanbit-5 | M76: Generation II (Upgraded in the 1980s,1990s and 2000s after Chernobyl) | O76: PWR (OPR-1000) | P76: 992 | Q76: 79.2 | R76: =IF(Q76>75,Q76,"") -> 79.2
L77: Wolsong-4 | M77: Generation II (Upgraded in the 1980s,1990s and 2000s after Chernobyl) | O77: PHWR (CANDU 6) | P77: 567 | Q77: 92.3 | R77: =IF(Q77>75,Q77,"") -> 92.3
... L85: Hanul-1 | M85: Generation II (Upgraded in the 1980s,1990s and 2000s after Chernobyl) | O85: PWR (France CPI) | P85: 966 | Q85: 85.5 | R85: =IF(Q85>75,Q85,"") -> 85.5
L86: JAPAN | R86: =IF(Q86>75,Q86,"")
L87: Tsuruga 3 | M87: Generation III | O87: APWR | P87: 1538 | R87: =IF(Q87>75,Q87,"")
L88: Tsuruga 4 | M88: Generation III | O88: APWR | P88: 1538 | R88: =IF(Q88>75,Q88,"")
L89: Kaminoseki 1 | M89: Generation III | O89: ABWR | P89: 1373 | R89: =IF(Q89>75,Q89,"")
L90: Sendai 3 | M90: Generation III | O90: APWR | P90: 1590 | R90: =IF(Q90>75,Q90,"")
L91: Higashidori 2 - Tepco | M91: Generation III | O91: ABWR | P91: 1385 | R91: =IF(Q91>75,Q91,"")
L92: Hamaoka 6 | M92: Generation III | O92: ABWR | P92: 1380 | R92: =IF(Q92>75,Q92,"")
L93: Higashidori 2 - Tohoku | M93: Generation III | O93: ABWR | P93: 1385 | R93: =IF(Q93>75,Q93,"")
L94: Kaminoseki 2 | M94: Generation III | O94: ABWR | P94: 1373 | R94: =IF(Q94>75,Q94,"")
L95: Higashidori 1 | M95: Generation III | O95: ABWR | P95: 1385 | R95: =IF(Q95>75,Q95,"")
L96: Ohma 1 | M96: Generation III | O96: ABWR | P96: 1383 | R96: =IF(Q96>75,Q96,"")
L97: Shimane 3 | M97: Generation III | O97: ABWR | P97: 1373 | R97: =IF(Q97>75,Q97,"")
L98: Higashidori 1 | M98: Generation III | O98: ABWR | P98: 1100 | R98: =IF(Q98>75,Q98,"")
L99: Higashidori 2 | M99: Generation III | O99: ABWR | P99: 1385 | R99: =IF(Q99>75,Q99,"")
L100: Shika 1 | M100: Generation II | O100: BWR-5 | P100: 505 | Q100: 77.6 | R100: =IF(Q100>75,Q100,"") -> 77.6
L101: Tomari-3 | M101: Generation II (Upgraded in the 1980s,1990s and 2000s after Chernobyl) | O101: PWR (M (3-loop)) | P101: 866 | R101: =IF(Q101>75,Q101,"")
L102: Shika-2 | M102: Generation III | O102: BWR (ABWR) | P102: 1108 | R102: =IF(Q102>75,Q102,"")
L103: Higashi Dori-1 | M103: Generation II (Upgraded in the 1980s,1990s and 2000s after Chernobyl) | O103: BWR (BWR-5) | P103: 1067 | R103: =IF(Q103>75,Q103,"")
L104: Hamaoka-5 | M104: Generation III | O104: BWR (ABWR) | P104: 1325 | R104: =IF(Q104>75,Q104,"")
L105: Onagawa-3 | M105: Generation II (Upgraded in the 1980s,1990s and 2000s after Chernobyl) | O105: BWR (BWR-5) | P105: 796 | R105: =IF(Q105>75,Q105,"")
L106: Kashiwazaki kariwa-7 | M106: Generation III | O106: BWR (ABWR) | P106: 1315 | R106: =IF(Q106>75,Q106,"")
L107: Genkai-4 | M107: Generation II (Upgraded in the 1980s,1990s and 2000s after Chernobyl) | O107: PWR (M (4-loop)) | P107: 1127 | Q107: 64.6 | R107: =IF(Q107>75,Q107,"")
L108: Kashiwazaki kariwa-6 | M108: Generation III | O108: BWR (ABWR) | P108: 1315 | R108: =IF(Q108>75,Q108,"")
L109: Onagawa-2 | M109: Generation II (Upgraded in the 1980s,1990s and 2000s after Chernobyl) | O109: BWR (BWR-5) | P109: 796 | R109: =IF(Q109>75,Q109,"")
L110: Ikata-3 | M110: Generation II (Upgraded in the 1980s,1990s and 2000s after Chernobyl) | O110: PWR (M (3-loop)) | P110: 846 | Q110: 64.8 | R110: =IF(Q110>75,Q110,"")
L111: Kashiwazaki kariwa-4 | M111: Generation II (Upgraded in the 1980s,1990s and 2000s after Chernobyl) | O111: BWR (BWR-5) | P111: 1067 | R111: =IF(Q111>75,Q111,"")
L112: Genkai-3 | M112: Generation II (Upgraded in the 1980s,1990s and 2000s after Chernobyl) | O112: PWR (M (4-loop)) | P112: 1127 | Q112: 63.3 | R112: =IF(Q112>75,Q112,"")
L113: Hamaoka-4 | M113: Generation II (Upgraded in the 1980s,1990s and 2000s after Chernobyl) | O113: BWR (BWR-5) | P113: 1092 | R113: =IF(Q113>75,Q113,"")
L114: Shika-2 | M114: Generation II (Upgraded in the 1980s,1990s and 2000s after Chernobyl) | O114: BWR (BWR-5) | P114: 505 | R114: =IF(Q114>75,Q114,"")
L115: Kashiwazaki kariwa-3 | M115: Generation II (Upgraded in the 1980s,1990s and 2000s after Chernobyl) | O115: BWR (BWR-5) | P115: 1067 | R115: =IF(Q115>75,Q115,"")
...

Sheet CAPEX
A1: Cost escalation rate during preconstruction and construction period (r) [%] | B1: 0.019551524
A2: Depreciacijska doba [let] | B2: 40
A3: Podaljšanje gradnje zaradi priprave dokumentacije [let] | B3: 4.5 | C3: Min construction period
A4: Podaljšanje gradnje zaradi prestavitve RTP, 400 kV stikališča, 3 400 kV daljnovodov in 7 100 kV povezav ob predpostavki sklenjenega sporazuma med investitorjem in ELES [let] | B4: 0 | C4: {=MIN(IF(ISNA(D9:D89), "",D9:D89))} -> 8.5
A5: Povečanje OCC initial za seizmično nadgradnjo lokacije + ostale postavke [EUR2024/kW] | B5: =495.63+200*0.5 -> 595.63 | C5: Max construction period
A6: Minimalna vrednost OCC initial | B6: {=MIN(IF(ISNA(G9:G89), "",G9:G89))} -> 3613.1181 | C6: {=MAX(IF(ISNA(D9:D89), "",D9:D89))} -> 29.5
A7: Maksimalna vrednost OCC initial | B7: {=MAX(IF(ISNA(G9:G89), "",G9:G89))} -> 11991.264
A8: JEDRSKA ELEKTRARNA | B8: Država | C8: Čas gradnje [let] | D8: Čas gradnje povečan za planiranje in prestavitev elektroenergetske infrastrukture [let] | E8: OCC initial [EUR2024/kW] | F8: OCC initial, povečan za seizmiko [EUR2024/kW] | G8: OCC initial, povečan za seizmiko, ostale jek2-povezane postavke in delno prilagoje za Južno Korejo [EUR2024/kW] | H8: Capacity factor - proba, ne uporabljaš
A9: Olkiluoto 3 | B9: FI | C9: 18 | D9: =IF(ISNUMBER(C9+SUM($B$3:$B$4)),C9+SUM($B$3:$B$4),NA()) -> 22.5 | E9: 4466.6043 | F9: =IF(ISNUMBER(E9+$B$5),E9+$B$5,NA()) -> 5062.2343 | G9: =F9 -> 5062.2343 | H9: =IFERROR(VLOOKUP(A9,'Capacity factor'!$L$7:$R$129,6,FALSE),"")
A10: Flamanville 3 | B10: FR | C10: 18 | D10: =IF(ISNUMBER(C10+SUM($B$3:$B$4)),C10+SUM($B$3:$B$4),NA()) -> 22.5 | E10: 3030.7655 | F10: =IF(ISNUMBER(E10+$B$5),E10+$B$5,NA()) -> 3626.3955 | G10: =F10 -> 3626.3955 | H10: =IFERROR(VLOOKUP(A10,'Capacity factor'!$L$7:$R$129,6,FALSE),"") | I10: Koliko vrednosti upoštevano v distribucijo | J10: =COUNT(G9:G89) -> 46
A11: Vogtle-4 | B11: US | C11: 10 | D11: =IF(ISNUMBER(C11+SUM($B$3:$B$4)),C11+SUM($B$3:$B$4),NA()) -> 14.5 | E11: 6352.62 | F11: =IF(ISNUMBER(E11+$B$5),E11+$B$5,NA()) -> 6948.25 | G11: =F11 -> 6948.25 | H11: =IFERROR(VLOOKUP(A11,'Capacity factor'!$L$7:$R$129,6,FALSE),"") -> 0 | I11: Koliko vrednosti upoštevano v distribucijo | J11: =COUNT(D9:D89) -> 23
A12: Vogtle-3 | B12: US | C12: 10 | D12: =IF(ISNUMBER(C12+SUM($B$3:$B$4)),C12+SUM($B$3:$B$4),NA()) -> 14.5 | E12: 6352.62 | F12: =IF(ISNUMBER(E12+$B$5),E12+$B$5,NA()) -> 6948.25 | G12: =F12 -> 6948.25 | H12: =IFERROR(VLOOKUP(A12,'Capacity factor'!$L$7:$R$129,6,FALSE),"") -> 99.3
A13: Shin Hanul 2 | B13: KOR | C13: 11 | D13: #N/A | E13: 3086.0791 | F13: =IF(ISNUMBER(E13+$B$5),E13+$B$5,NA()) -> 3681.7091 | G13: #N/A | H13: =IFERROR(VLOOKUP(A13,'Capacity factor'!$L$7:$R$129,6,FALSE),"") -> 0
A14: Shin Hanul 1 | B14: KOR | C14: 10 | D14: #N/A | E14: 3161.6379 | F14: =IF(ISNUMBER(E14+$B$5),E14+$B$5,NA()) -> 3757.2679 | G14: #N/A | H14: =IFERROR(VLOOKUP(A14,'Capacity factor'!$L$7:$R$129,6,FALSE),"") -> 99.5 | I14: Min
A15: Saeul 2 | B15: KOR | C15: 10 | D15: =IF(ISNUMBER(C15+SUM($B$3:$B$4)),C15+SUM($B$3:$B$4),NA()) -> 14.5 | E15: #DIV/0! | F15: =IF(ISNUMBER(E15+$B$5),E15+$B$5,NA()) -> #N/A | G15: =F15 -> #N/A | H15: =IFERROR(VLOOKUP(A15,'Capacity factor'!$L$7:$R$129,6,FALSE),"") -> 83.9 | I15: Max
A16: Saeul 1 | B16: KOR | C16: 8 | D16: =IF(ISNUMBER(C16+SUM($B$3:$B$4)),C16+SUM($B$3:$B$4),NA()) -> 12.5 | E16: #DIV/0! | F16: =IF(ISNUMBER(E16+$B$5),E16+$B$5,NA()) -> #N/A | G16: =F16 -> #N/A | H16: =IFERROR(VLOOKUP(A16,'Capacity factor'!$L$7:$R$129,6,FALSE),"") -> 79.2
A17: Shin Wolsong-2 | B17: KOR | C17: 7 | D17: #N/A | E17: 2698.7702 | F17: =IF(ISNUMBER(E17+$B$5),E17+$B$5,NA()) -> 3294.4002 | G17: #N/A | H17: =IFERROR(VLOOKUP(A17,'Capacity factor'!$L$7:$R$129,6,FALSE),"") -> 85.4
A18: Shin Kori-5/6 | B18: KOR | C18: 7 | D18: =IF(ISNUMBER(C18+SUM($B$3:$B$4)),C18+SUM($B$3:$B$4),NA()) -> 11.5 | E18: 4631.2532 | F18: =IF(ISNUMBER(E18+$B$5),E18+$B$5,NA()) -> 5226.8832 | G18: =F18 -> 5226.8832 | H18: =IFERROR(VLOOKUP(A18,'Capacity factor'!$L$7:$R$129,6,FALSE),"")
A19: Shin Kori-3/4 | B19: KOR | C19: 11 | D19: =IF(ISNUMBER(C19+SUM($B$3:$B$4)),C19+SUM($B$3:$B$4),NA()) -> 15.5 | E19: 3830.1851 | F19: =IF(ISNUMBER(E19+$B$5),E19+$B$5,NA()) -> 4425.8151 | G19: =F19 -> 4425.8151 | H19: =IFERROR(VLOOKUP(A19,'Capacity factor'!$L$7:$R$129,6,FALSE),"")
A20: Shin Kori-2 | B20: KOR | C20: 5 | D20: =IF(ISNUMBER(C20+SUM($B$3:$B$4)),C20+SUM($B$3:$B$4),NA()) -> 9.5 | E20: #DIV/0! | F20: =IF(ISNUMBER(E20+$B$5),E20+$B$5,NA()) -> #N/A | G20: =F20 -> #N/A | H20: =IFERROR(VLOOKUP(A20,'Capacity factor'!$L$7:$R$129,6,FALSE),"") -> 83.7
A21: Shin Wolsong-1 | B21: KOR | C21: 5 | D21: #N/A | E21: 2692.8096 | F21: =IF(ISNUMBER(E21+$B$5),E21+$B$5,NA()) -> 3288.4396 | G21: #N/A | H21: =IFERROR(VLOOKUP(A21,'Capacity factor'!$L$7:$R$129,6,FALSE),"") -> 82.9
A22: Shin Kori 1 | B22: KOR | C22: 5 | D22: =IF(ISNUMBER(C22+SUM($B$3:$B$4)),C22+SUM($B$3:$B$4),NA()) -> 9.5 | E22: #DIV/0! | F22: =IF(ISNUMBER(E22+$B$5),E22+$B$5,NA()) -> #N/A | G22: =F22 -> #N/A | H22: =IFERROR(VLOOKUP(A22,'Capacity factor'!$L$7:$R$129,6,FALSE),"") -> 76.1
A23: Hanul-6 | B23: KOR | C23: 5 | D23: =IF(ISNUMBER(C23+SUM($B$3:$B$4)),C23+SUM($B$3:$B$4),NA()) -> 9.5 | E23: #DIV/0! | F23: =IF(ISNUMBER(E23+$B$5),E23+$B$5,NA()) -> #N/A | G23: =F23 -> #N/A | H23: =IFERROR(VLOOKUP(A23,'Capacity factor'!$L$7:$R$129,6,FALSE),"") -> 88.6
A24: Hanul-5 | B24: KOR | C24: 5 | D24: =IF(ISNUMBER(C24+SUM($B$3:$B$4)),C24+SUM($B$3:$B$4),NA()) -> 9.5 | E24: #DIV/0! | F24: =IF(ISNUMBER(E24+$B$5),E24+$B$5,NA()) -> #N/A | G24: =F24 -> #N/A | H24: =IFERROR(VLOOKUP(A24,'Capacity factor'!$L$7:$R$129,6,FALSE),"") -> 88.2
A25: Hanbit-6 | B25: KOR | C25: 5 | D25: =IF(ISNUMBER(C25+SUM($B$3:$B$4)),C25+SUM($B$3:$B$4),NA()) -> 9.5 | E25: 4244.7431 | F25: =IF(ISNUMBER(E25+$B$5),E25+$B$5,NA()) -> 4840.3731 | G25: =F25 -> 4840.3731 | H25: =IFERROR(VLOOKUP(A25,'Capacity factor'!$L$7:$R$129,6,FALSE),"") -> 85.1
A26: Hanbit-5 | B26: KOR | C26: 5 | D26: =IF(ISNUMBER(C26+SUM($B$3:$B$4)),C26+SUM($B$3:$B$4),NA()) -> 9.5 | E26: 4247.096 | F26: =IF(ISNUMBER(E26+$B$5),E26+$B$5,NA()) -> 4842.726 | G26: =F26 -> 4842.726 | H26: =IFERROR(VLOOKUP(A26,'Capacity factor'!$L$7:$R$129,6,FALSE),"") -> 79.2
A27: Tomari-3 | B27: JP | C27: 5 | D27: =IF(ISNUMBER(C27+SUM($B$3:$B$4)),C27+SUM($B$3:$B$4),NA()) -> 9.5 | E27: 3812.0106 | F27: =IF(ISNUMBER(E27+$B$5),E27+$B$5,NA()) -> 4407.6406 | G27: =F27 -> 4407.6406
A28: Shika-2 | B28: JP | C28: 5 | D28: =IF(ISNUMBER(C28+SUM($B$3:$B$4)),C28+SUM($B$3:$B$4),NA()) -> 9.5 | E28: 4607.2352 | F28: =IF(ISNUMBER(E28+$B$5),E28+$B$5,NA()) -> 5202.8652 | G28: =F28 -> 5202.8652
A29: Higashi Dori-1 | B29: JP | C29: 5 | D29: =IF(ISNUMBER(C29+SUM($B$3:$B$4)),C29+SUM($B$3:$B$4),NA()) -> 9.5 | E29: 4971.277 | F29: =IF(ISNUMBER(E29+$B$5),E29+$B$5,NA()) -> 5566.907 | G29: =F29 -> 5566.907
A30: Hamaoka-5 | B30: JP | C30: 5 | D30: =IF(ISNUMBER(C30+SUM($B$3:$B$4)),C30+SUM($B$3:$B$4),NA()) -> 9.5 | E30: 3536.9758 | F30: =IF(ISNUMBER(E30+$B$5),E30+$B$5,NA()) -> 4132.6058 | G30: =F30 -> 4132.6058
A31: Onagawa-3 | B31: JP | C31: 4 | D31: =IF(ISNUMBER(C31+SUM($B$3:$B$4)),C31+SUM($B$3:$B$4),NA()) -> 8.5 | E31: 4859.4197 | F31: =IF(ISNUMBER(E31+$B$5),E31+$B$5,NA()) -> 5455.0497 | G31: =F31 -> 5455.0497
A32: Hinkley Point C1 | B32: UK | C32: 15 | D32: =IF(ISNUMBER(C32+SUM($B$3:$B$4)),C32+SUM($B$3:$B$4),NA()) -> 19.5 | E32: 9313.741 | F32: =IF(ISNUMBER(E32+$B$5),E32+$B$5,NA()) -> 9909.371 | G32: =F32 -> 9909.371
A33: Hinkley Point C2 | B33: UK | C33: 15 | D33: =IF(ISNUMBER(C33+SUM($B$3:$B$4)),C33+SUM($B$3:$B$4),NA()) -> 19.5 | E33: 9313.741 | F33: =IF(ISNUMBER(E33+$B$5),E33+$B$5,NA()) -> 9909.371 | G33: =F33 -> 9909.371
A34: Turkey point 7 | B34: US | C34: #VALUE! | D34: =IF(ISNUMBER(C34+SUM($B$3:$B$4)),C34+SUM($B$3:$B$4),NA()) -> #N/A | E34: 4001.6883 | F34: =IF(ISNUMBER(E34+$B$5),E34+$B$5,NA()) -> 4597.3183 | G34: =F34 -> 4597.3183
A35: Turkey point 7* | B35: US | C35: #VALUE! | D35: =IF(ISNUMBER(C35+SUM($B$3:$B$4)),C35+SUM($B$3:$B$4),NA()) -> #N/A | E35: 3441.4353 | F35: =IF(ISNUMBER(E35+$B$5),E35+$B$5,NA()) -> 4037.0653 | G35: =F35 -> 4037.0653
A36: Turkey point 6 | B36: US | C36: #VALUE! | D36: =IF(ISNUMBER(C36+SUM($B$3:$B$4)),C36+SUM($B$3:$B$4),NA()) -> #N/A | E36: 3441.4353 | F36: =IF(ISNUMBER(E36+$B$5),E36+$B$5,NA()) -> 4037.0653 | G36: =F36 -> 4037.0653
A37: Fermi 3 | B37: US | C37: #VALUE! | D37: =IF(ISNUMBER(C37+SUM($B$3:$B$4)),C37+SUM($B$3:$B$4),NA()) -> #N/A | E37: 3611.8682 | F37: =IF(ISNUMBER(E37+$B$5),E37+$B$5,NA()) -> 4207.4982 | G37: =F37 -> 4207.4982
A38: Ohma 1 | B38: JP | C38: 22 | D38: =IF(ISNUMBER(C38+SUM($B$3:$B$4)),C38+SUM($B$3:$B$4),NA()) -> 26.5 | E38: #DIV/0! | F38: =IF(ISNUMBER(E38+$B$5),E38+$B$5,NA()) -> #N/A | G38: =F38 -> #N/A
A39: Shimane 3 | B39: JP | C39: 25 | D39: =IF(ISNUMBER(C39+SUM($B$3:$B$4)),C39+SUM($B$3:$B$4),NA()) -> 29.5 | E39: #DIV/0! | F39: =IF(ISNUMBER(E39+$B$5),E39+$B$5,NA()) -> #N/A | G39: =F39 -> #N/A
A40: Temelin 4 (Češka) | B40: CZ | C40: #VALUE! | D40: =IF(ISNUMBER(C40+SUM($B$3:$B$4)),C40+SUM($B$3:$B$4),NA()) -> #N/A | E40: 6545.6302 | F40: =IF(ISNUMBER(E40+$B$5),E40+$B$5,NA()) -> 7141.2602 | G40: =F40 -> 7141.2602
A41: Temelin 3 (Češka) | B41: CZ | C41: #VALUE! | D41: =IF(ISNUMBER(C41+SUM($B$3:$B$4)),C41+SUM($B$3:$B$4),NA()) -> #N/A | E41: 6545.6302 | F41: =IF(ISNUMBER(E41+$B$5),E41+$B$5,NA()) -> 7141.2602 | G41: =F41 -> 7141.2602
A42: Dukovany 6 (Češka) | B42: CZ | C42: #VALUE! | D42: =IF(ISNUMBER(C42+SUM($B$3:$B$4)),C42+SUM($B$3:$B$4),NA()) -> #N/A | E42: 6360.7254 | F42: =IF(ISNUMBER(E42+$B$5),E42+$B$5,NA()) -> 6956.3554 | G42: =F42 -> 6956.3554
A43: Dukovany 5 (Češka) | B43: CZ | C43: #VALUE! | D43: =IF(ISNUMBER(C43+SUM($B$3:$B$4)),C43+SUM($B$3:$B$4),NA()) -> #N/A | E43: 6060.945 | F43: =IF(ISNUMBER(E43+$B$5),E43+$B$5,NA()) -> 6656.575 | G43: =F43 -> 6656.575
A44: Hanhikivi 1 | B44: FI | C44: #VALUE! | D44: =IF(ISNUMBER(C44+SUM($B$3:$B$4)),C44+SUM($B$3:$B$4),NA()) -> #N/A | E44: 8772.7637 | F44: =IF(ISNUMBER(E44+$B$5),E44+$B$5,NA()) -> 9368.3937 | G44: =F44 -> 9368.3937
A45: Olkiluoto 4 | B45: FI | C45: #VALUE! | D45: =IF(ISNUMBER(C45+SUM($B$3:$B$4)),C45+SUM($B$3:$B$4),NA()) -> #N/A | E45: #VALUE! | F45: =IF(ISNUMBER(E45+$B$5),E45+$B$5,NA()) -> #N/A | G45: =F45 -> #N/A
B46: PL | C46: #VALUE! | D46: =IF(ISNUMBER(C46+SUM($B$3:$B$4)),C46+SUM($B$3:$B$4),NA()) -> #N/A | E46: #VALUE! | F46: =IF(ISNUMBER(E46+$B$5),E46+$B$5,NA()) -> #N/A | G46: =F46 -> #N/A
A47: Patnow 2 (Poljska) | B47: PL | C47: #VALUE! | D47: =IF(ISNUMBER(C47+SUM($B$3:$B$4)),C47+SUM($B$3:$B$4),NA()) -> #N/A | E47: 4973.6139 | F47: =IF(ISNUMBER(E47+$B$5),E47+$B$5,NA()) -> 5569.2439 | G47: =F47 -> 5569.2439
A48: Patnow 2* (Poljska) | B48: PL | C48: #VALUE! | D48: =IF(ISNUMBER(C48+SUM($B$3:$B$4)),C48+SUM($B$3:$B$4),NA()) -> #N/A | E48: 7460.9644 | F48: =IF(ISNUMBER(E48+$B$5),E48+$B$5,NA()) -> 8056.5944 | G48: =F48 -> 8056.5944
A49: Patnow 1 (Poljska) | B49: PL | C49: #VALUE! | D49: =IF(ISNUMBER(C49+SUM($B$3:$B$4)),C49+SUM($B$3:$B$4),NA()) -> #N/A | E49: #VALUE! | F49: =IF(ISNUMBER(E49+$B$5),E49+$B$5,NA()) -> #N/A | G49: =F49 -> #N/A
A50: Lubiatowa-Kopalina 3 | B50: PL | C50: #VALUE! | D50: =IF(ISNUMBER(C50+SUM($B$3:$B$4)),C50+SUM($B$3:$B$4),NA()) -> #N/A | E50: 5065.823 | F50: =IF(ISNUMBER(E50+$B$5),E50+$B$5,NA()) -> 5661.453 | G50: =F50 -> 5661.453
A51: Lubiatowa-Kopalina 3* | B51: PL | C51: #VALUE! | D51: =IF(ISNUMBER(C51+SUM($B$3:$B$4)),C51+SUM($B$3:$B$4),NA()) -> #N/A | E51: 7599.2881 | F51: =IF(ISNUMBER(E51+$B$5),E51+$B$5,NA()) -> 8194.9181 | G51: =F51 -> 8194.9181
A52: Lubiatowa-Kopalina 2 | B52: PL | C52: #VALUE! | D52: =IF(ISNUMBER(C52+SUM($B$3:$B$4)),C52+SUM($B$3:$B$4),NA()) -> #N/A | E52: #VALUE! | F52: =IF(ISNUMBER(E52+$B$5),E52+$B$5,NA()) -> #N/A | G52: =F52 -> #N/A
A53: Lubiatowa-Kopalina 1 | B53: PL | C53: #VALUE! | D53: =IF(ISNUMBER(C53+SUM($B$3:$B$4)),C53+SUM($B$3:$B$4),NA()) -> #N/A | E53: #VALUE! | F53: =IF(ISNUMBER(E53+$B$5),E53+$B$5,NA()) -> #N/A | G53: =F53 -> #N/A
A54: Planned | B54: HU | C54: #VALUE! | D54: =IF(ISNUMBER(C54+SUM($B$3:$B$4)),C54+SUM($B$3:$B$4),NA()) -> #N/A | E54: 7305.0002 | F54: =IF(ISNUMBER(E54+$B$5),E54+$B$5,NA()) -> 7900.6302 | G54: =F54 -> 7900.6302
A55: Planned | B55: HU | C55: #VALUE! | D55: =IF(ISNUMBER(C55+SUM($B$3:$B$4)),C55+SUM($B$3:$B$4),NA()) -> #N/A | E55: 7305.0002 | F55: =IF(ISNUMBER(E55+$B$5),E55+$B$5,NA()) -> 7900.6302 | G55: =F55 -> 7900.6302
A56: Kozloduy 8 | B56: BG | C56: #VALUE! | D56: =IF(ISNUMBER(C56+SUM($B$3:$B$4)),C56+SUM($B$3:$B$4),NA()) -> #N/A | E56: 5502.0309 | F56: =IF(ISNUMBER(E56+$B$5),E56+$B$5,NA()) -> 6097.6609 | G56: =F56 -> 6097.6609
A57: Kozloduy 7 | B57: BG | C57: #VALUE! | D57: =IF(ISNUMBER(C57+SUM($B$3:$B$4)),C57+SUM($B$3:$B$4),NA()) -> #N/A | E57: 5502.0309 | F57: =IF(ISNUMBER(E57+$B$5),E57+$B$5,NA()) -> 6097.6609 | G57: =F57 -> 6097.6609
A58: New energy strategy-1NPP | B58: SE | C58: #VALUE! | D58: =IF(ISNUMBER(C58+SUM($B$3:$B$4)),C58+SUM($B$3:$B$4),NA()) -> #N/A | E58: #VALUE! | F58: =IF(ISNUMBER(E58+$B$5),E58+$B$5,NA()) -> #N/A | G58: =F58 -> #N/A
A59: New energy strategy-1NPP | B59: SE | C59: #VALUE! | D59: =IF(ISNUMBER(C59+SUM($B$3:$B$4)),C59+SUM($B$3:$B$4),NA()) -> #N/A | E59: #VALUE! | F59: =IF(ISNUMBER(E59+$B$5),E59+$B$5,NA()) -> #N/A | G59: =F59 -> #N/A
A60: Borssele 3 | B60: NL | C60: #VALUE! | D60: =IF(ISNUMBER(C60+SUM($B$3:$B$4)),C60+SUM($B$3:$B$4),NA()) -> #N/A | E60: 6253.3544 | F60: =IF(ISNUMBER(E60+$B$5),E60+$B$5,NA()) -> 6848.9844 | G60: =F60 -> 6848.9844
A61: Borssele 3* | B61: NL | C61: #VALUE! | D61: =IF(ISNUMBER(C61+SUM($B$3:$B$4)),C61+SUM($B$3:$B$4),NA()) -> #N/A | E61: 10005.367 | F61: =IF(ISNUMBER(E61+$B$5),E61+$B$5,NA()) -> 10600.997 | G61: =F61 -> 10600.997
A62: Borssele 2 | B62: NL | C62: #VALUE! | D62: =IF(ISNUMBER(C62+SUM($B$3:$B$4)),C62+SUM($B$3:$B$4),NA()) -> #N/A | E62: 4828.8871 | F62: =IF(ISNUMBER(E62+$B$5),E62+$B$5,NA()) -> 5424.5171 | G62: =F62 -> 5424.5171
A63: Borssele 2* | B63: NL | C63: #VALUE! | D63: =IF(ISNUMBER(C63+SUM($B$3:$B$4)),C63+SUM($B$3:$B$4),NA()) -> #N/A | E63: 7726.2194 | F63: =IF(ISNUMBER(E63+$B$5),E63+$B$5,NA()) -> 8321.8494 | G63: =F63 -> 8321.8494
A64: JEK 2 | B64: SI | C64: #VALUE! | D64: =IF(ISNUMBER(C64+SUM($B$3:$B$4)),C64+SUM($B$3:$B$4),NA()) -> #N/A | E64: 9424.8746 | F64: =IF(ISNUMBER(E64+$B$5),E64+$B$5,NA()) -> 10020.505 | G64: =F64 -> 10020.505
A65: Penly 2 | B65: FR | C65: #VALUE! | D65: =IF(ISNUMBER(C65+SUM($B$3:$B$4)),C65+SUM($B$3:$B$4),NA()) -> #N/A | E65: 7221.9032 | F65: =IF(ISNUMBER(E65+$B$5),E65+$B$5,NA()) -> 7817.5332 | G65: =F65 -> 7817.5332
A66: Penly 1 | B66: FR | C66: #VALUE! | D66: =IF(ISNUMBER(C66+SUM($B$3:$B$4)),C66+SUM($B$3:$B$4),NA()) -> #N/A | E66: 7221.9032 | F66: =IF(ISNUMBER(E66+$B$5),E66+$B$5,NA()) -> 7817.5332 | G66: =F66 -> 7817.5332
A67: Gravelines 2 | B67: FR | C67: #VALUE! | D67: =IF(ISNUMBER(C67+SUM($B$3:$B$4)),C67+SUM($B$3:$B$4),NA()) -> #N/A | E67: 7221.9032 | F67: =IF(ISNUMBER(E67+$B$5),E67+$B$5,NA()) -> 7817.5332 | G67: =F67 -> 7817.5332
A68: Gravelines 1 | B68: FR | C68: #VALUE! | D68: =IF(ISNUMBER(C68+SUM($B$3:$B$4)),C68+SUM($B$3:$B$4),NA()) -> #N/A | E68: 7221.9032 | F68: =IF(ISNUMBER(E68+$B$5),E68+$B$5,NA()) -> 7817.5332 | G68: =F68 -> 7817.5332
A69: Bugey 2 | B69: FR | C69: #VALUE! | D69: =IF(ISNUMBER(C69+SUM($B$3:$B$4)),C69+SUM($B$3:$B$4),NA()) -> #N/A | E69: 7221.9032 | F69: =IF(ISNUMBER(E69+$B$5),E69+$B$5,NA()) -> 7817.5332 | G69: =F69 -> 7817.5332
A70: Bugey 1 | B70: FR | C70: #VALUE! | D70: =IF(ISNUMBER(C70+SUM($B$3:$B$4)),C70+SUM($B$3:$B$4),NA()) -> #N/A | E70: 7221.9032 | F70: =IF(ISNUMBER(E70+$B$5),E70+$B$5,NA()) -> 7817.5332 | G70: =F70 -> 7817.5332
A71: Bradwell 2 | B71: UK | C71: #VALUE! | D71: =IF(ISNUMBER(C71+SUM($B$3:$B$4)),C71+SUM($B$3:$B$4),NA()) -> #N/A | E71: #VALUE! | F71: =IF(ISNUMBER(E71+$B$5),E71+$B$5,NA()) -> #N/A | G71: =F71 -> #N/A
A72: Bradwell 1 | B72: UK | C72: #VALUE! | D72: =IF(ISNUMBER(C72+SUM($B$3:$B$4)),C72+SUM($B$3:$B$4),NA()) -> #N/A | E72: #DIV/0! | F72: =IF(ISNUMBER(E72+$B$5),E72+$B$5,NA()) -> #N/A | G72: =F72 -> #N/A
A73: Sizewell C2 | B73: UK | C73: #VALUE! | D73: =IF(ISNUMBER(C73+SUM($B$3:$B$4)),C73+SUM($B$3:$B$4),NA()) -> #N/A | E73: 11395.634 | F73: =IF(ISNUMBER(E73+$B$5),E73+$B$5,NA()) -> 11991.264 | G73: =F73 -> 11991.264
A74: Sizewell C1 | B74: UK | C74: #VALUE! | D74: =IF(ISNUMBER(C74+SUM($B$3:$B$4)),C74+SUM($B$3:$B$4),NA()) -> #N/A | E74: 11395.634 | F74: =IF(ISNUMBER(E74+$B$5),E74+$B$5,NA()) -> 11991.264 | G74: =F74 -> 11991.264
A75: Clinch River | B75: US | C75: #VALUE! | D75: =IF(ISNUMBER(C75+SUM($B$3:$B$4)),C75+SUM($B$3:$B$4),NA()) -> #N/A | E75: #DIV/0! | F75: =IF(ISNUMBER(E75+$B$5),E75+$B$5,NA()) -> #N/A | G75: =F75 -> #N/A
A76: Bellefonte 2 | B76: US | C76: #VALUE! | D76: =IF(ISNUMBER(C76+SUM($B$3:$B$4)),C76+SUM($B$3:$B$4),NA()) -> #N/A | E76: #DIV/0! | F76: =IF(ISNUMBER(E76+$B$5),E76+$B$5,NA()) -> #N/A | G76: =F76 -> #N/A
A77: Salem 3 | B77: US | C77: #VALUE! | D77: =IF(ISNUMBER(C77+SUM($B$3:$B$4)),C77+SUM($B$3:$B$4),NA()) -> #N/A | E77: #DIV/0! | F77: =IF(ISNUMBER(E77+$B$5),E77+$B$5,NA()) -> #N/A | G77: =F77 -> #N/A
A78: Shin Hanul 4 | B78: KOR | C78: #VALUE! | D78: =IF(ISNUMBER(C78+SUM($B$3:$B$4)),C78+SUM($B$3:$B$4),NA()) -> #N/A | E78: 3017.4881 | F78: =IF(ISNUMBER(E78+$B$5),E78+$B$5,NA()) -> 3613.1181 | G78: #N/A
A79: Shin Hanul 3 | B79: KOR | C79: #VALUE! | D79: =IF(ISNUMBER(C79+SUM($B$3:$B$4)),C79+SUM($B$3:$B$4),NA()) -> #N/A | E79: 3017.4881 | F79: =IF(ISNUMBER(E79+$B$5),E79+$B$5,NA()) -> 3613.1181 | G79: =F79 -> 3613.1181
A80: Tsuruga 3 | B80: JP | C80: #VALUE! | D80: =IF(ISNUMBER(C80+SUM($B$3:$B$4)),C80+SUM($B$3:$B$4),NA()) -> #N/A | E80: #DIV/0! | F80: =IF(ISNUMBER(E80+$B$5),E80+$B$5,NA()) -> #N/A | G80: =F80 -> #N/A
A81: Tsuruga 4 | B81: JP | C81: #VALUE! | D81: =IF(ISNUMBER(C81+SUM($B$3:$B$4)),C81+SUM($B$3:$B$4),NA()) -> #N/A | E81: #DIV/0! | F81: =IF(ISNUMBER(E81+$B$5),E81+$B$5,NA()) -> #N/A | G81: =F81 -> #N/A
A82: Kaminoseki 1 | B82: JP | C82: #VALUE! | D82: =IF(ISNUMBER(C82+SUM($B$3:$B$4)),C82+SUM($B$3:$B$4),NA()) -> #N/A | E82: #DIV/0! | F82: =IF(ISNUMBER(E82+$B$5),E82+$B$5,NA()) -> #N/A | G82: =F82 -> #N/A
A83: Sendai 3 | B83: JP | C83: #VALUE! | D83: =IF(ISNUMBER(C83+SUM($B$3:$B$4)),C83+SUM($B$3:$B$4),NA()) -> #N/A | E83: #DIV/0! | F83: =IF(ISNUMBER(E83+$B$5),E83+$B$5,NA()) -> #N/A | G83: =F83 -> #N/A
A84: Higashidori 2 - Tepco | B84: JP | C84: #VALUE! | D84: =IF(ISNUMBER(C84+SUM($B$3:$B$4)),C84+SUM($B$3:$B$4),NA()) -> #N/A | E84: #DIV/0! | F84: =IF(ISNUMBER(E84+$B$5),E84+$B$5,NA()) -> #N/A | G84: =F84 -> #N/A
A85: Hamaoka 6 | B85: JP | C85: #VALUE! | D85: =IF(ISNUMBER(C85+SUM($B$3:$B$4)),C85+SUM($B$3:$B$4),NA()) -> #N/A | E85: #DIV/0! | F85: =IF(ISNUMBER(E85+$B$5),E85+$B$5,NA()) -> #N/A | G85: =F85 -> #N/A
A86: Higashidori 2 - Tohoku | B86: JP | C86: #VALUE! | D86: =IF(ISNUMBER(C86+SUM($B$3:$B$4)),C86+SUM($B$3:$B$4),NA()) -> #N/A | E86: #DIV/0! | F86: =IF(ISNUMBER(E86+$B$5),E86+$B$5,NA()) -> #N/A | G86: =F86 -> #N/A
A87: Kaminoseki 2 | B87: JP | C87: #VALUE! | D87: =IF(ISNUMBER(C87+SUM($B$3:$B$4)),C87+SUM($B$3:$B$4),NA()) -> #N/A | E87: #DIV/0! | F87: =IF(ISNUMBER(E87+$B$5),E87+$B$5,NA()) -> #N/A | G87: =F87 -> #N/A
A88: Higashidori 1 | B88: JP | C88: #VALUE! | D88: =IF(ISNUMBER(C88+SUM($B$3:$B$4)),C88+SUM($B$3:$B$4),NA()) -> #N/A | E88: #DIV/0! | F88: =IF(ISNUMBER(E88+$B$5),E88+$B$5,NA()) -> #N/A | G88: =F88 -> #N/A
A89: Higashidori 2 | B89: JP | C89: #VALUE! | D89: =IF(ISNUMBER(C89+SUM($B$3:$B$4)),C89+SUM($B$3:$B$4),NA()) -> #N/A | E89: #DIV/0! | F89: =IF(ISNUMBER(E89+$B$5),E89+$B$5,NA()) -> #N/A | G89: =F89 -> #N/A

Sheet WACC
A1: STRUKTURA FINANCIRANJA | B1: Delež | C1: Ročnost | D1: Min | E1: Mean | F1: Max
A2: Lastniški kapital - mala vloga države | B2: 0 | D2: 0 | E2: 0 | F2: 0
A3: Lastniški kapital - velika vloga države | B3: 0.25 | D3: 0.014 | E3: 0.10486438 | F3: 0.20531985 | G3: VELIKA VLOGA DRŽAVE
A4: Izvozni kredit - velika vloga države | B4: 0.25 | C4: 18 | D4: -0.0062745098 | E4: 0.016431048 | F4: 0.041470588
A5: Krediti pri bankah z in brez državnega poroštva - velika vloga države | B5: 0.15 | C5: 20 | D5: -0.014588235 | E5: 0.023706842 | F5: 0.05977451
A6: Obveznice (dolžniški vrednostni papirji) - velika vloga države | B6: 0.35 | C6: 50 | D6: -0.0099215686 | E6: 0.020588235 | F6: 0.032254902
A7: Izvozni kredit | B7: 0 | D7: 0 | E7: 0 | F7: 0 | G7: MALA VLOGA DRŽAVE
A8: Krediti pri bankah z in brez državnega poroštva | B8: 0 | D8: 0 | E8: 0 | F8: 0
A9: Obveznice (dolžniški vrednostni papirji) | B9: 0 | D9: 0 | E9: 0 | F9: 0
A10: Strošek odobritve kredita, različne provizije pri izdaji | B10: 0.008

Sheet Stroški nadgradnje na 80 let
A1: Podaljšanje življenske dobe do 80 let
A2: Vzamemo povprečje iz slik Gen Energije
A3: Obdobje 41-60 let [EUR/kW/20 let] | B3: 629.5
A4: Obdobje 41-60 let [EUR/kW/leto] | B4: 0

Sheet O&M
H1: Povprečni podatki ameriških elektrarn [USD2022/MWh] | L1: Študija delež fixed vs flexible | M1: 175 | N1: USD/leto | P1: str 8 https://inldigitallibrary.inl.gov/sites/sti/sti/Sort_107010.pdf
H2: Single unit | I2: 26.09 | M2: =M1*(1000*M10) -> 218750000 | N2: letni fiksni stroški
H3: Multiple_unit | I3: 17.01 | M3: =M10*M9*8760 -> 9891500 | N3: proizvedene EE
H4: Podatek za JEK2 [USD2022/MWh] | I4: =I3*0.25+I2*0.75 -> 23.82 | J4: predpostavka, da se podaljša življenska doba JEK1 še za 20 let | M4: =M2/M3 -> 22.114947 | N4: USD/MWh fiksni
A5: Povp. fiksni O&M skozi vseh 80 let[EUR/kW] | B5: =I8 -> 155.99592 | C5: Share of Fiskni =%M 41-60 | D5: Izračun po deležih | E5: Average | F5: razmerja iz gen energija študije | H5: Podatek za JEK2 [EUR2022/MWh] | I5: 22.685714 | M5: 2.8 | N5: USD/MWh variabilni
A6: Fiksni O&M 0-20 [EUR/kW] | B6: =C6*B8 -> 73.409843 | C6: 0.3 | D6: =C6*D8 -> 73.409843 | E6: =AVERAGE(D6:D9) -> 155.99592 | H6: Podatek za JEK2 [EUR2024/MWh] | I6: 22.209314 | M6: =M4/SUM(M4:M5) -> 0.88761766 | N6: delež fiksnih
A7: Fiksni O&M 21-40 [EUR/kW] | B7: =B8*C7 -> 183.52461 | C7: 0.75 | D7: =C7*D8 -> 183.52461 | H7: Fiskni OM [EUR2024/MWh] | I7: =I6*M6 -> 19.71338 | M7: =M5/SUM(M4:M5) -> 0.11238234 | N7: delež variabilnih
A8: Fiksni O&M 41-60 [EUR/kW] | B8: =B5/(SUM(C6:C9))*4 -> 244.69948 | C8: 1 | D8: =B8 -> 244.69948 | H8: Fiskni OM [EUR2024/kW] | I8: =I7*M3/(M10*1000) -> 155.99592
A9: Fiksni O&M 61-80 [EUR/kW] | B9: =B8*C9 -> 122.34974 | C9: 0.5 | D9: =C9*D8 -> 122.34974 | H9: Variabilni OM [EUR2024/MWh] | I9: =I6*M7 -> 2.4959347 | M9: ='Capacity factor'!$B$5 -> 0.90333333 | N9: Capacity factor (za zdaj dokler ni končne vrednosti)
H10: Zmerni stroški v €/kWe leto - 2024 | I10: 205.70175 | M10: ='Inštalirana kapaciteta'!B2 -> 1250 | N10: povprečna moč JE
A11: Razmerje 75 % in 50 % (Table 38 - https://inldigitallibrary.inl.gov/sites/sti/sti/Sort_107010.pdf) | B11: =I11 -> 239.78947 | C11: =I10 -> 205.70175 | D11: =B11/C11 -> 1.1657143 | E11: Max | H11: Konzervativni stroški v €/kWe leto - 2024 | I11: 239.78947
A12: Razmerje 25% in 50% (Table 38 - https://inldigitallibrary.inl.gov/sites/sti/sti/Sort_107010.pdf) | B12: =I10 -> 205.70175 | C12: =I12 -> 148.10526 | D12: =C12/B12 -> 0.72 | E12: Min | H12: Napredni stroški v €/kWe leto - 2024 | I12: 148.10526
A16: Variabilni O&M stroški [EUR/MWh] | B16: =I9 -> 2.4959347
A18: Stroški obratovanja in vzdrževanja | B18: Min | C18: Srednja vrednost | D18: Max
A19: Fiksni O&M 1-20 let [EUR/kW] | B19: =$D$12*C19 -> 52.855087 | C19: =B6 -> 73.409843 | D19: =$D$11*C19 -> 85.574902
A20: Fiksni O&M 21-40 let [EUR/kW] | B20: =$D$12*C20 -> 132.13772 | C20: =B7 -> 183.52461 | D20: =$D$11*C20 -> 213.93726
A21: Fiksni O&M 41-60 let [EUR/kW] | B21: =$D$12*C21 -> 176.18362 | C21: =B8 -> 244.69948 | D21: =$D$11*C21 -> 285.24967
A22: Fiksni O&M 61-80 let [EUR/kW] | B22: =$D$12*C22 -> 88.091811 | C22: =B9 -> 122.34974 | D22: =$D$11*C22 -> 142.62484
A23: Real escalation rate [%/year] | B23: 0.005
A24: =A16 -> Variabilni O&M stroški [EUR/MWh] | B24: =C24*D12 -> 1.7970729 | C24: =B16 -> 2.4959347 | D24: =C24*D11 -> 2.9095467
A25: Verjetnost, da se pojavijo vrednosti desno od povprečja [%] | B25: 0.55
A26: Verjetnost, da se pojavijo vrednosti levo od povprečja [%] | B26: =1-B25 -> 0.45
A27: Delež fiksnih O&M stroškov v času gradnje glede na povprečne O&M stroške za časa obratovanja [%] | B27: 0 | C27: Za zdaj ni O&M stroškov tekom gradnje, sam so notri v OCC
A28: Povprečni stroški O&M skozi 80 let [EUR/kW] | B28: =$B$5 -> 155.99592

Sheet Fuel cost
A1: Fuel cost min [EUR2024/MWh] | B1: 6.46
A2: Fuel cost mean [EUR2024/MWh] | B2: 8.23
A3: Fuel cost max [EUR2024/MWh] | B3: 9.52
A4: Real cost escalation [%] | B4: 0
A5: Verjetnost, da se pojavijo vrednosti levo od povprečja [%] | B5: =1-B6 -> 0.45
A6: Verjetnost, da se pojavijo vrednosti desno od povprečja [%] | B6: 0.55

Sheet Extraordinary repairs
A1: Hitre samodejne ustavitve v obdobju delovanju 1983-2023 | B1: 82 | C1: JEK1 vir | D1: ! VKLJUČEN V DRUGIH STROŠKIH, ZATO TRENUTNO 0
A2: Hitre ročne ustavitve v obdobju delovanju 1983-2023 | B2: 5 | C2: JEK1 vir
A3: Prisilne ustavitve v obdobju delovanju 1983-2023 | B3: 27 | C3: JEK1 vir
A4: Skupaj nenačrtovanih ustavitev | B4: =SUM(B1:B3) -> 114
A5: Število nepričakovanih izpadov na leto | B5: 0
A6: Strošek nepričakovanega remonta - tehnično popravilo [EUR] | B6: 0
A7: Strošek nepričakovanega remonta - izgube zaradi potrebe po nakupu EE iz trga in izgube nevariabilne cene stroškovne cene EE [EUR] | B7: 0
A8: Skupen strošek nepričakovanega remonta [EUR] | B8: =SUM(B6:B7) -> 0
A9: Fiksna stroškovna cena proizvodnje EE, zmanjšana za variabilne stroške (tj. goriva) [EUR/MWh] | B9: =43.74-8 -> 35.74 | C9: JEK2 vir
A10: Kolikšen delež leta v povprečju takšen dogodek traja oz. faktor prisilne ustavitve [delež leta] | B10: 0.0116 | C10: JEK1 vir
A11: Povprečen capacity factor [%] | B11: ='Capacity factor'!$B$5 -> 0.90333333 | C11: Zgodovinski podatki za vse zahodne JE
A12: Cost escalation rate [%] | B12: 0

Sheet Stroški odpadkov
A1: 40 LET | K1: Escalation rate - MZPP | L1: 0.005 | N1: Finančni podatki | R1: JEK2 - Capacity factor - GEN-E | S1: NEK - Capacity factor - GEN-E | T1: Capacity faktor - MZPP | U1: Ur v letu dni
A2: Jedrska elektrarna | B2: Moč reaktorja (MW) | C2: Cena ravnanja z odpadki 2020-2023 (mio. €) | D2: Cena ravnanja z odpadki 2024 (mio. €) | E2: Cena ravnanja z odpadki 2024 [EUR] | F2: Cena ravnanja z odpadki povečana za escalation rate (y + 40) | G2: Letno plačilo, da v 40 letih pridemo do končne investicijske vrednosti | H2: Preverba, da prideš do istih cifer | I2: Strošek (€/MW/leto) | J2: Strošek (€/MWh) | K2: Povprečje let | L2: 40 | N2: Inflacija iz leta 2020 do sredine 2024 | O2: Inflacija iz leta 2021 do sredine 2024 | P2: Inflacija iz leta 2023 do sredine 2024 | Q2: Inflacija iz leta 2022 do sredine 2024 | R2: 0.93 | S2: 0.9 | T2: ='Capacity factor'!$B$5 -> 0.90333333 | U2: 8760
A3: Loviisa-2 (Finska) | B3: 507 | C3: =L17*(B3/SUM(B3:B4)) -> 426.15274 | D3: =C3*$Q$3 -> 417.20353 | E3: =D3*1000000 -> 4.1720353e+08 | F3: =FV($L$1,$L$2,,-E3,1) -> 5.0931967e+08 | G3: =PMT($L$3,$L$2,,-F3,1) -> 7809092.4 | H3: {=SUM(G3*(1+$L$3)^ROW(INDIRECT("1:"&$L$2)))} -> 5.0931967e+08 | I3: =G3/(SUM(B3)) -> 15402.549 | J3: =I3/($T$2*$U$2) -> 1.9464375 | K3: Interest rate - MZPP | L3: 0.0225 | N3: =1.34 -> 1.34 | O3: =1.127 -> 1.127 | P3: 1.002 | Q3: 0.979 | R3: Escalation rate - GEN | S3: 0
A4: Olkiluoto-3 (Finska) | B4: 1575 | C4: =L17*(B4/SUM(B3:B4)) -> 1323.8473 | D4: =C4*$Q$3 -> 1296.0465 | E4: =D4*1000000 -> 1.2960465e+09 | F4: =FV($L$1,$L$2,,-E4,1) -> 1.5822061e+09 | G4: =PMT($L$3,$L$2,,-F4,1) -> 24259015 | H4: {=SUM(G4*(1+$L$3)^ROW(INDIRECT("1:"&$L$2)))} -> 1.5822061e+09 | I4: =G4/(SUM(B4)) -> 15402.549 | J4: =I4/($T$2*$U$2) -> 1.9464375 | R4: Interest rate - GEN | S4: =0.015 -> 0.015
A5: =A3 -> Loviisa-2 (Finska) | I5: =I3 -> 15402.549 | J5: =I5/($T$2*$U$2) -> 1.9464375 | K5: Strošek (€/MW/leto) | M5: Strošek (€/MWh)
A6: =A4 -> Olkiluoto-3 (Finska) | I6: =I4 -> 15402.549 | J6: =I6/($T$2*$U$2) -> 1.9464375 | K6: Min | L6: =MIN(I3:I17) -> 14349.779 | M6: Min | N6: =MIN(J3:J17) -> 1.8133977
A7: Barseback 2 (Švedska) | B7: 600 | C7: =$L$20*(B7/SUM($B$7:$B$12)) -> 469.8521 | D7: =C7*$Q$3 -> 459.98521 | E7: =D7*1000000 -> 4.5998521e+08 | F7: =FV($L$1,$L$2,,-E7,1) -> 5.6154729e+08 | G7: =PMT($L$3,$L$2,,-F7,1) -> 8609867.2 | H7: {=SUM(G7*(1+$L$3)^ROW(INDIRECT("1:"&$L$2)))} -> 5.6154729e+08 | I7: =G7/(SUM(B7)) -> 14349.779 | J7: =I7/($T$2*$U$2) -> 1.8133977 | K7: Average | L7: =AVERAGE(I3:I17) -> 20581.443 | M7: Average | N7: =AVERAGE(J3:J17) -> 2.5951395
A8: Forsmark 2 (Švedska) | B8: 1121 | C8: =$L$20*(B8/SUM($B$7:$B$12)) -> 877.84035 | D8: =C8*$Q$3 -> 859.4057 | E8: =D8*1000000 -> 8.594057e+08 | F8: =FV($L$1,$L$2,,-E8,1) -> 1.0491575e+09 | G8: =PMT($L$3,$L$2,,-F8,1) -> 16086102 | H8: {=SUM(G8*(1+$L$3)^ROW(INDIRECT("1:"&$L$2)))} -> 1.0491575e+09 | I8: =G8/(SUM(B8)) -> 14349.779 | J8: =I8/($T$2*$U$2) -> 1.8133977 | K8: Max | L8: =MAX(I3:I17) -> 58991.718 | M8: Max | N8: =MAX(J3:J17) -> 7.4548499
A9: Forsmark 3 (Švedska) | B9: 1172 | C9: =$L$20*(B9/SUM($B$7:$B$12)) -> 917.77777 | D9: =C9*$Q$3 -> 898.50444 | E9: =D9*1000000 -> 8.9850444e+08 | F9: =FV($L$1,$L$2,,-E9,1) -> 1.096889e+09 | G9: =PMT($L$3,$L$2,,-F9,1) -> 16817941 | H9: {=SUM(G9*(1+$L$3)^ROW(INDIRECT("1:"&$L$2)))} -> 1.096889e+09 | I9: =G9/(SUM(B9)) -> 14349.779 | J9: =I9/($T$2*$U$2) -> 1.8133977 | K9: Min distribucije | L9: =$L$6 -> 14349.779 | M9: Min distribucije | N9: =$N$6 -> 1.8133977
A10: Oskarshamn 3 (Švedska) | B10: 1400 | C10: =$L$20*(B10/SUM($B$7:$B$12)) -> 1096.3216 | D10: =C10*$Q$3 -> 1073.2988 | E10: =D10*1000000 -> 1.0732988e+09 | F10: =FV($L$1,$L$2,,-E10,1) -> 1.310277e+09 | G10: =PMT($L$3,$L$2,,-F10,1) -> 20089690 | H10: {=SUM(G10*(1+$L$3)^ROW(INDIRECT("1:"&$L$2)))} -> 1.310277e+09 | I10: =G10/(SUM(B10)) -> 14349.779 | J10: =I10/($T$2*$U$2) -> 1.8133977 | K10: Max distribucije | L10: =$L$8 -> 58991.718 | M10: Max distribucije | N10: =$N$8 -> 7.4548499
A11: Ringhals 3 (Švedska) | B11: 1081 | C11: =$L$20*(B11/SUM($B$7:$B$12)) -> 846.51687 | D11: =C11*$Q$3 -> 828.74002 | E11: =D11*1000000 -> 8.2874002e+08 | F11: =FV($L$1,$L$2,,-E11,1) -> 1.011721e+09 | G11: =PMT($L$3,$L$2,,-F11,1) -> 15512111 | H11: {=SUM(G11*(1+$L$3)^ROW(INDIRECT("1:"&$L$2)))} -> 1.011721e+09 | I11: =G11/(SUM(B11)) -> 14349.779 | J11: =I11/($T$2*$U$2) -> 1.8133977 | K11: * povprečje treh vrednosti | L11: =AVERAGE((306+147),(317+172),(394+198)) -> 511.33333 | M11: ** Delitev moči NEK na dva dela
A12: Ringhals 4 (Švedska) | B12: 1130 | C12: =$L$20*(B12/SUM($B$7:$B$12)) -> 884.88813 | D12: =C12*$Q$3 -> 866.30548 | E12: =D12*1000000 -> 8.6630548e+08 | F12: =FV($L$1,$L$2,,-E12,1) -> 1.0575807e+09 | G12: =PMT($L$3,$L$2,,-F12,1) -> 16215250 | H12: {=SUM(G12*(1+$L$3)^ROW(INDIRECT("1:"&$L$2)))} -> 1.0575807e+09 | I12: =G12/(SUM(B12)) -> 14349.779 | J12: =I12/($T$2*$U$2) -> 1.8133977 | K12: Kak delež stroškov ostane pri švicarjih | L12: 0.5
A13: JEK1 | B13: 696 | C13: 1845 (2024) | D13: =1845 -> 1845 | E13: =D13*1000000 -> 1845000000 | F13: =FV($L$1,$L$2,,-E13,1) -> 2.2523654e+09 | G13: =PMT($L$3,$L$2,,-F13,1) -> 34534165 | H13: {=SUM(G13*(1+$L$3)^ROW(INDIRECT("1:"&$L$2)))} -> 2.2523654e+09 | I13: =G13/(SUM(B13)) -> 49618.053 | J13: =I13/($S$2*$U$2) -> 6.2935125
A14: JEK2* | B14: =1250 -> 1250 | C14: 3227 (2024) | D14: =3227*C74 -> 1041.5861 | E14: =D14*1000000 -> 1.0415861e+09 | F14: =FV($S$3,$L$2,,-E14,1) -> 1.0415861e+09 | G14: =PMT($S$4,$L$2,,-F14,1) -> 18909767 | H14: {=SUM(G14*(1+$S$4)^ROW(INDIRECT("1:"&$L$2)))} -> 1.0415861e+09 | I14: =G14/(SUM(B14)) -> 15127.814 | J14: =I14/($R$2*$U$2) -> 1.8569026
A15: JEK2* | B15: =1250 -> 1250 | C15: 3227 (2024) | D15: =3227*C74 -> 1041.5861 | E15: =D15*1000000 -> 1.0415861e+09 | F15: =FV($S$3,$L$2,,-E15,1) -> 1.0415861e+09 | G15: =PMT($S$4,$L$2,,-F15,1) -> 18909767 | H15: {=SUM(G15*(1+$S$4)^ROW(INDIRECT("1:"&$L$2)))} -> 1.0415861e+09 | I15: =G15/(SUM(B15)) -> 15127.814 | J15: =I15/($R$2*$U$2) -> 1.8569026 | K15: Strošek investicije Finske - celoten | L15: 7000 | M15: 221 milijard Švedskih kron (2022)
A16: Gosgen (Švica) | B16: 1010 | C16: 4751 (2020) | D16: =4751*N3*L12 -> 3183.17 | E16: =D16*1000000 -> 3183170000 | F16: =FV($L$1,$L$2,,-E16,1) -> 3.8859956e+09 | G16: =PMT($L$3,$L$2,,-F16,1) -> 59581635 | H16: {=SUM(G16*(1+$L$3)^ROW(INDIRECT("1:"&$L$2)))} -> 3.8859956e+09 | I16: =G16/(SUM(B16)) -> 58991.718 | J16: =I16/($T$2*$U$2) -> 7.4548499 | K16: Koliko prevzamejo mlajše elektrarne (2/5) | L16: 0.25 | M16: Pretvornik valute v €
A17: Nova češka JE | I17: =$D$87 -> 22147.376 | J17: =I17/($T$2*$U$2) -> 2.7987889 | K17: Strošek investicije Finske - novejše | L17: =L16*L15 -> 1750 | M17: 10.62
A18: 60 LET | K18: Strošek investicije Švedske | L18: =M19 -> 20372.787 | M18: Skupna cena ravnanja z odpadki v mio. € (2024)
A19: =A2 -> Jedrska elektrarna | B19: =B2 -> Moč reaktorja (MW) | C19: =C2 -> Cena ravnanja z odpadki 2020-2023 (mio. €) | D19: =D2 -> Cena ravnanja z odpadki 2024 (mio. €) | E19: =E2 -> Cena ravnanja z odpadki 2024 [EUR] | F19: Cena razgradnje povečana za escalation rate (y + 60) | G19: Letno plačilo, da v 60 letih pridemo do končne investicijske vrednosti | H19: Preverba, da prideš do istih cifer | I19: Strošek (€/MW/leto) | J19: Strošek (€/MWh) | K19: =K16 -> Koliko prevzamejo mlajše elektrarne (2/5) | L19: =L16 -> 0.25 | M19: =(221000000000/10.62)/1000000*Q3 -> 20372.787
A20: Loviisa-2 (Finska) | B20: 507 | C20: =$L$17*(B20/SUM(B20:B21)) -> 426.15274 | D20: =C20*$Q$3 -> 417.20353 | E20: =D20*1000000 -> 4.1720353e+08 | F20: =FV($L$1,$L$22,,-E20,1) -> 5.6274505e+08 | G20: =PMT($L$3,$L$22,,-F20,1) -> 4422338.1 | H20: {=SUM(G20*(1+$L$3)^ROW(INDIRECT("1:"&$L$22)))} -> 5.6274505e+08 | I20: =G20/(SUM(B20)) -> 8722.5604 | J20: =I20/($T$2*$U$2) -> 1.1022798 | K20: Strošek investicije Švedska - novejše | L20: =L19*L18 -> 5093.1968
A21: Olkiluoto-3 (Finska) | B21: 1575 | C21: =$L$17*(B21/SUM(B20:B21)) -> 1323.8473 | D21: =C21*$Q$3 -> 1296.0465 | E21: =D21*1000000 -> 1.2960465e+09 | F21: =FV($L$1,$L$22,,-E21,1) -> 1.7481725e+09 | G21: =PMT($L$3,$L$22,,-F21,1) -> 13738033 | H21: {=SUM(G21*(1+$L$3)^ROW(INDIRECT("1:"&$L$22)))} -> 1.7481725e+09 | I21: =G21/(SUM(B21)) -> 8722.5604 | J21: =I21/($T$2*$U$2) -> 1.1022798
A22: =A20 -> Loviisa-2 (Finska) | I22: =I20 -> 8722.5604 | J22: =I22/($T$2*$U$2) -> 1.1022798 | K22: Leta | L22: 60
A23: =A21 -> Olkiluoto-3 (Finska) | I23: =I21 -> 8722.5604 | J23: =I23/($T$2*$U$2) -> 1.1022798 | K23: Strošek (€/MW/leto) | M23: Strošek (€/MWh)
A24: Barseback 2 (Švedska) | B24: 600 | C24: =$L$20*(B24/SUM($B$7:$B$12)) -> 469.8521 | D24: =C24*$Q$3 -> 459.98521 | E24: =D24*1000000 -> 4.5998521e+08 | F24: =FV($L$1,$L$22,,-E24,1) -> 6.2045112e+08 | G24: =PMT($L$3,$L$22,,-F24,1) -> 4875821.9 | H24: {=SUM(G24*(1+$L$3)^ROW(INDIRECT("1:"&$L$22)))} -> 6.2045112e+08 | I24: =G24/(SUM(B24)) -> 8126.3699 | J24: =I24/($T$2*$U$2) -> 1.0269385 | K24: Min | L24: =MIN(I20:I34) -> 8126.3699 | M24: Min | N24: =MIN(J20:J34) -> 1.0269385
A25: Forsmark 2 (Švedska) | B25: 1121 | C25: =$L$20*(B25/SUM($B$7:$B$12)) -> 877.84035 | D25: =C25*$Q$3 -> 859.4057 | E25: =D25*1000000 -> 8.594057e+08 | F25: =FV($L$1,$L$22,,-E25,1) -> 1.1592095e+09 | G25: =PMT($L$3,$L$22,,-F25,1) -> 9109660.7 | H25: {=SUM(G25*(1+$L$3)^ROW(INDIRECT("1:"&$L$22)))} -> 1.1592095e+09 | I25: =G25/(SUM(B25)) -> 8126.3699 | J25: =I25/($T$2*$U$2) -> 1.0269385 | K25: Average | L25: =AVERAGE(I20:I34) -> 11650.808 | M25: Average | N25: =AVERAGE(J20:J34) -> 1.4690801
A26: Forsmark 3 (Švedska) | B26: 1172 | C26: =$L$20*(B26/SUM($B$7:$B$12)) -> 917.77777 | D26: =C26*$Q$3 -> 898.50444 | E26: =D26*1000000 -> 8.9850444e+08 | F26: =FV($L$1,$L$22,,-E26,1) -> 1.2119479e+09 | G26: =PMT($L$3,$L$22,,-F26,1) -> 9524105.5 | H26: {=SUM(G26*(1+$L$3)^ROW(INDIRECT("1:"&$L$22)))} -> 1.2119479e+09 | I26: =G26/(SUM(B26)) -> 8126.3699 | J26: =I26/($T$2*$U$2) -> 1.0269385 | K26: Max | L26: =MAX(I20:I34) -> 33407.381 | M26: Max | N26: =MAX(J20:J34) -> 4.2217284
A27: Oskarshamn 3 (Švedska) | B27: 1400 | C27: =$L$20*(B27/SUM($B$7:$B$12)) -> 1096.3216 | D27: =C27*$Q$3 -> 1073.2988 | E27: =D27*1000000 -> 1.0732988e+09 | F27: =FV($L$1,$L$22,,-E27,1) -> 1.4477193e+09 | G27: =PMT($L$3,$L$22,,-F27,1) -> 11376918 | H27: {=SUM(G27*(1+$L$3)^ROW(INDIRECT("1:"&$L$22)))} -> 1.4477193e+09 | I27: =G27/(SUM(B27)) -> 8126.3699 | J27: =I27/($T$2*$U$2) -> 1.0269385 | K27: Min distribucije | L27: =$L$24 -> 8126.3699 | M27: Min distribucije | N27: =$N$24 -> 1.0269385
A28: Ringhals 3 (Švedska) | B28: 1081 | C28: =$L$20*(B28/SUM($B$7:$B$12)) -> 846.51687 | D28: =C28*$Q$3 -> 828.74002 | E28: =D28*1000000 -> 8.2874002e+08 | F28: =FV($L$1,$L$22,,-E28,1) -> 1.1178461e+09 | G28: =PMT($L$3,$L$22,,-F28,1) -> 8784605.9 | H28: {=SUM(G28*(1+$L$3)^ROW(INDIRECT("1:"&$L$22)))} -> 1.1178461e+09 | I28: =G28/(SUM(B28)) -> 8126.3699 | J28: =I28/($T$2*$U$2) -> 1.0269385 | K28: Max distribucije | L28: =$L$8 -> 58991.718 | M28: Max distribucije | N28: =$N$26 -> 4.2217284
A29: Ringhals 4 (Švedska) | B29: 1130 | C29: =$L$20*(B29/SUM($B$7:$B$12)) -> 884.88813 | D29: =C29*$Q$3 -> 866.30548 | E29: =D29*1000000 -> 8.6630548e+08 | F29: =FV($L$1,$L$22,,-E29,1) -> 1.1685163e+09 | G29: =PMT($L$3,$L$22,,-F29,1) -> 9182798 | H29: {=SUM(G29*(1+$L$3)^ROW(INDIRECT("1:"&$L$22)))} -> 1.1685163e+09 | I29: =G29/(SUM(B29)) -> 8126.3699 | J29: =I29/($T$2*$U$2) -> 1.0269385
A30: JEK1 | B30: 696 | C30: =C13 -> 1845 (2024) | D30: =D13 -> 1845 | E30: =D30*1000000 -> 1845000000 | F30: =FV($L$1,$L$22,,-E30,1) -> 2.4886285e+09 | G30: =PMT($L$3,$L$22,,-F30,1) -> 19556915 | H30: {=SUM(G30*(1+$L$3)^ROW(INDIRECT("1:"&$L$22)))} -> 2.4886285e+09 | I30: =G30/(SUM(B30)) -> 28099.015 | J30: =I30/($S$2*$U$2) -> 3.5640557 | K30: * povprečje treh vrednosti | L30: =AVERAGE((306+147),(317+172),(394+198)) -> 511.33333 | M30: ** Delitev moči NEK na dva dela
A31: JEK2* | B31: =1250 -> 1250 | C31: 3227 (2024) | D31: =3227*C74 -> 1041.5861 | E31: =D31*1000000 -> 1.0415861e+09 | F31: =FV($S$3,$L$22,,-E31,1) -> 1.0415861e+09 | G31: =PMT($S$4,$L$22,,-F31,1) -> 10665665 | H31: {=SUM(G31*(1+$S$4)^ROW(INDIRECT("1:"&$L$22)))} -> 1.0415861e+09 | I31: =G31/(SUM(B31)) -> 8532.532 | J31: =I31/($R$2*$U$2) -> 1.0473477
A32: JEK2* | B32: =1250 -> 1250 | C32: 3227 (2024) | D32: =3227*C74 -> 1041.5861 | E32: =D32*1000000 -> 1.0415861e+09 | F32: =FV($S$3,$L$22,,-E32,1) -> 1.0415861e+09 | G32: =PMT($S$4,$L$22,,-F32,1) -> 10665665 | H32: {=SUM(G32*(1+$S$4)^ROW(INDIRECT("1:"&$L$22)))} -> 1.0415861e+09 | I32: =G32/(SUM(B32)) -> 8532.532 | J32: =I32/($R$2*$U$2) -> 1.0473477
A33: Gosgen (Švica) | B33: 1010 | C33: 4751 (2020) | D33: =4751*$N$3*$L$12 -> 3183.17 | E33: =D33*1000000 -> 3183170000 | F33: =FV($L$1,$L$22,,-E33,1) -> 4.2936193e+09 | G33: =PMT($L$3,$L$22,,-F33,1) -> 33741455 | H33: {=SUM(G33*(1+$L$3)^ROW(INDIRECT("1:"&$L$22)))} -> 4.2936193e+09 | I33: =G33/(SUM(B33)) -> 33407.381 | J33: =I33/($T$2*$U$2) -> 4.2217284
A34: Nova češka JE | I34: =$C$87 -> 12542.198 | J34: =I34/($T$2*$U$2) -> 1.5849718
A35: 80 LET
A36: =A19 -> Jedrska elektrarna | B36: =B19 -> Moč reaktorja (MW) | C36: =C19 -> Cena ravnanja z odpadki 2020-2023 (mio. €) | D36: =D19 -> Cena ravnanja z odpadki 2024 (mio. €) | E36: =E19 -> Cena ravnanja z odpadki 2024 [EUR] | F36: Cena razgradnje povečana za escalation rate (y + 80) | G36: Letno plačilo, da v 80 letih pridemo do končne investicijske vrednosti | H36: Preverba, da prideš do istih cifer | I36: Strošek (€/MW/leto) | J36: Strošek (€/MWh) | K36: Leta | L36: 80
A37: Loviisa-2 (Finska) | B37: 507 | C37: =$L$17*(B37/SUM(B37:B38)) -> 426.15274 | D37: =C37*$Q$3 -> 417.20353 | E37: =D37*1000000 -> 4.1720353e+08 | F37: =FV($L$1,$L$36,,-E37,1) -> 6.2177451e+08 | G37: =PMT($L$3,$L$36,,-F37,1) -> 2775187.9 | H37: {=SUM(G37*(1+$L$3)^ROW(INDIRECT("1:"&$L$36)))} -> 6.2177451e+08 | I37: =G37/(SUM(B37)) -> 5473.7435 | J37: =I37/($T$2*$U$2) -> 0.69172313 | K37: Strošek (€/MW/leto) | M37: Strošek (€/MWh)
A38: Olkiluoto-3 (Finska) | B38: 1575 | C38: =$L$17*(B38/SUM(B37:B38)) -> 1323.8473 | D38: =C38*$Q$3 -> 1296.0465 | E38: =D38*1000000 -> 1.2960465e+09 | F38: =FV($L$1,$L$36,,-E38,1) -> 1.931548e+09 | G38: =PMT($L$3,$L$36,,-F38,1) -> 8621145.9 | H38: {=SUM(G38*(1+$L$3)^ROW(INDIRECT("1:"&$L$36)))} -> 1.931548e+09 | I38: =G38/(SUM(B38)) -> 5473.7435 | J38: =I38/($T$2*$U$2) -> 0.69172313 | K38: Min | L38: =MIN(I37:I51) -> 5099.6109 | M38: Min | N38: =MIN(J37:J51) -> 0.64444357 | O38: GEN-E (delež za odpadke) - Strošek (€/MWh)
A39: =A37 -> Loviisa-2 (Finska) | I39: =I37 -> 5473.7435 | J39: =I39/($T$2*$U$2) -> 0.69172313 | K39: Average | L39: =AVERAGE(I37:I51) -> 7314.1829 | M39: Average | N39: =AVERAGE(J37:J51) -> 0.92034361 | O39: =2*0.3 -> 0.6
A40: =A38 -> Olkiluoto-3 (Finska) | I40: =I38 -> 5473.7435 | J40: =I40/($T$2*$U$2) -> 0.69172313 | K40: Max | L40: =MAX(I37:I51) -> 20964.421 | M40: Max | N40: =MAX(J37:J51) -> 2.6492976
A41: Barseback 2 (Švedska) | B41: 600 | C41: =$L$20*(B41/SUM($B$7:$B$12)) -> 469.8521 | D41: =C41*$Q$3 -> 459.98521 | E41: =D41*1000000 -> 4.5998521e+08 | F41: =FV($L$1,$L$36,,-E41,1) -> 6.855337e+08 | G41: =PMT($L$3,$L$36,,-F41,1) -> 3059766.5 | H41: {=SUM(G41*(1+$L$3)^ROW(INDIRECT("1:"&$L$36)))} -> 6.855337e+08 | I41: =G41/(SUM(B41)) -> 5099.6109 | J41: =I41/($T$2*$U$2) -> 0.64444357 | K41: Min distribucije | L41: =$L$38 -> 5099.6109 | M41: Min distribucije | N41: =$N$38 -> 0.64444357
A42: Forsmark 2 (Švedska) | B42: 1121 | C42: =$L$20*(B42/SUM($B$7:$B$12)) -> 877.84035 | D42: =C42*$Q$3 -> 859.4057 | E42: =D42*1000000 -> 8.594057e+08 | F42: =FV($L$1,$L$36,,-E42,1) -> 1.2808055e+09 | G42: =PMT($L$3,$L$36,,-F42,1) -> 5716663.8 | H42: {=SUM(G42*(1+$L$3)^ROW(INDIRECT("1:"&$L$36)))} -> 1.2808055e+09 | I42: =G42/(SUM(B42)) -> 5099.6109 | J42: =I42/($T$2*$U$2) -> 0.64444357 | K42: Max distribucije | L42: =$L40 -> 20964.421 | M42: Max distribucije | N42: =$N$40 -> 2.6492976
A43: Forsmark 3 (Švedska) | B43: 1172 | C43: =$L$20*(B43/SUM($B$7:$B$12)) -> 917.77777 | D43: =C43*$Q$3 -> 898.50444 | E43: =D43*1000000 -> 8.9850444e+08 | F43: =FV($L$1,$L$36,,-E43,1) -> 1.3390758e+09 | G43: =PMT($L$3,$L$36,,-F43,1) -> 5976744 | H43: {=SUM(G43*(1+$L$3)^ROW(INDIRECT("1:"&$L$36)))} -> 1.3390758e+09 | I43: =G43/(SUM(B43)) -> 5099.6109 | J43: =I43/($T$2*$U$2) -> 0.64444357
A44: Oskarshamn 3 (Švedska) | B44: 1400 | C44: =$L$20*(B44/SUM($B$7:$B$12)) -> 1096.3216 | D44: =C44*$Q$3 -> 1073.2988 | E44: =D44*1000000 -> 1.0732988e+09 | F44: =FV($L$1,$L$36,,-E44,1) -> 1.5995786e+09 | G44: =PMT($L$3,$L$36,,-F44,1) -> 7139455.2 | H44: {=SUM(G44*(1+$L$3)^ROW(INDIRECT("1:"&$L$36)))} -> 1.5995786e+09 | I44: =G44/(SUM(B44)) -> 5099.6109 | J44: =I44/($T$2*$U$2) -> 0.64444357 | K44: * povprečje treh vrednosti | L44: =AVERAGE((306+147),(317+172),(394+198)) -> 511.33333 | M44: ** Delitev moči NEK na dva dela
A45: Ringhals 3 (Švedska) | B45: 1081 | C45: =$L$20*(B45/SUM($B$7:$B$12)) -> 846.51687 | D45: =C45*$Q$3 -> 828.74002 | E45: =D45*1000000 -> 8.2874002e+08 | F45: =FV($L$1,$L$36,,-E45,1) -> 1.2351032e+09 | G45: =PMT($L$3,$L$36,,-F45,1) -> 5512679.4 | H45: {=SUM(G45*(1+$L$3)^ROW(INDIRECT("1:"&$L$36)))} -> 1.2351032e+09 | I45: =G45/(SUM(B45)) -> 5099.6109 | J45: =I45/($T$2*$U$2) -> 0.64444357
A46: Ringhals 4 (Švedska) | B46: 1130 | C46: =$L$20*(B46/SUM($B$7:$B$12)) -> 884.88813 | D46: =C46*$Q$3 -> 866.30548 | E46: =D46*1000000 -> 8.6630548e+08 | F46: =FV($L$1,$L$36,,-E46,1) -> 1.2910885e+09 | G46: =PMT($L$3,$L$36,,-F46,1) -> 5762560.3 | H46: {=SUM(G46*(1+$L$3)^ROW(INDIRECT("1:"&$L$36)))} -> 1.2910885e+09 | I46: =G46/(SUM(B46)) -> 5099.6109 | J46: =I46/($T$2*$U$2) -> 0.64444357
A47: JEK1 | B47: 696 | C47: =C13 -> 1845 (2024) | D47: =D13 -> 1845 | E47: =D47*1000000 -> 1845000000 | F47: =FV($L$1,$L$36,,-E47,1) -> 2.7496747e+09 | G47: =PMT($L$3,$L$36,,-F47,1) -> 12272719 | H47: {=SUM(G47*(1+$L$3)^ROW(INDIRECT("1:"&$L$36)))} -> 2.7496747e+09 | I47: =G47/(SUM(B47)) -> 17633.217 | J47: =I47/($S$2*$U$2) -> 2.2365826
A48: JEK2* | B48: =1250 -> 1250 | C48: 3227 (2024) | D48: =3227*$C$74 -> 1041.5861 | E48: =D48*1000000 -> 1.0415861e+09 | F48: =FV($S$3,$L$36,,-E48,1) -> 1.0415861e+09 | G48: =PMT($S$4,$L$36,,-F48,1) -> 6719844.9 | H48: {=SUM(G48*(1+$S$4)^ROW(INDIRECT("1:"&$L$36)))} -> 1.0415861e+09 | I48: =G48/(SUM(B48)) -> 5375.8759 | J48: =2*$C$74 -> 0.64554455
A49: JEK2* | B49: =1250 -> 1250 | C49: 3227 (2024) | D49: =3227*$C$74 -> 1041.5861 | E49: =D49*1000000 -> 1.0415861e+09 | F49: =FV($S$3,$L$36,,-E49,1) -> 1.0415861e+09 | G49: =PMT($S$4,$L$36,,-F49,1) -> 6719844.9 | H49: {=SUM(G49*(1+$S$4)^ROW(INDIRECT("1:"&$L$36)))} -> 1.0415861e+09 | I49: =G49/(SUM(B49)) -> 5375.8759 | J49: =2*$C$74 -> 0.64554455
A50: Gosgen (Švica) | B50: 1010 | C50: 4751 (2020) | D50: =4751*$N$3*$L$12 -> 3183.17 | E50: =D50*1000000 -> 3183170000 | F50: =FV($L$1,$L$36,,-E50,1) -> 4.744001e+09 | G50: =PMT($L$3,$L$36,,-F50,1) -> 21174066 | H50: {=SUM(G50*(1+$L$3)^ROW(INDIRECT("1:"&$L$36)))} -> 4.744001e+09 | I50: =G50/(SUM(B50)) -> 20964.421 | J50: =I50/($T$2*$U$2) -> 2.6492976
A51: Nova češka JE | I51: =E87 -> 7870.7138 | J51: =I51/($T$2*$U$2) -> 0.99463097
A52: 100 LET
A53: =A36 -> Jedrska elektrarna | B53: =B36 -> Moč reaktorja (MW) | C53: =C36 -> Cena ravnanja z odpadki 2020-2023 (mio. €) | D53: =D36 -> Cena ravnanja z odpadki 2024 (mio. €) | E53: =E36 -> Cena ravnanja z odpadki 2024 [EUR] | F53: Cena razgradnje povečana za escalation rate (y + 100) | G53: Letno plačilo, da v 100 letih pridemo do končne investicijske vrednosti | H53: Preverba, da prideš do istih cifer | I53: Strošek (€/MW/leto) | J53: Strošek (€/MWh) | K53: Leta | L53: 100
A54: Loviisa-2 (Finska) | B54: 507 | C54: =$L$17*(B54/SUM(B54:B55)) -> 426.15274 | D54: =C54*$Q$3 -> 417.20353 | E54: =D54*1000000 -> 4.1720353e+08 | F54: =FV($L$1,$L$53,,-E54,1) -> 6.8699591e+08 | G54: =PMT($L$3,$L$53,,-F54,1) -> 1831498 | H54: {=SUM(G54*(1+$L$3)^ROW(INDIRECT("1:"&$L$53)))} -> 6.8699591e+08 | I54: =G54/(SUM(B54)) -> 3612.4221 | J54: =I54/($T$2*$U$2) -> 0.45650585 | K54: Strošek (€/MW/leto) | M54: Strošek (€/MWh)
A55: Olkiluoto-3 (Finska) | B55: 1575 | C55: =$L$17*(B55/SUM(B54:B55)) -> 1323.8473 | D55: =C55*$Q$3 -> 1296.0465 | E55: =D55*1000000 -> 1.2960465e+09 | F55: =FV($L$1,$L$53,,-E55,1) -> 2.1341589e+09 | G55: =PMT($L$3,$L$53,,-F55,1) -> 5689564.8 | H55: {=SUM(G55*(1+$L$3)^ROW(INDIRECT("1:"&$L$53)))} -> 2.1341589e+09 | I55: =G55/(SUM(B55)) -> 3612.4221 | J55: =I55/($T$2*$U$2) -> 0.45650585 | K55: Min | L55: =MIN(I54:I68) -> 3365.5116 | M55: Min | N55: =MIN(J54:J68) -> 0.42530349
A56: =A54 -> Loviisa-2 (Finska) | I56: =I54 -> 3612.4221 | J56: =I56/($T$2*$U$2) -> 0.45650585 | K56: Average | L56: =AVERAGE(I54:I68) -> 4832.3894 | M56: Average | N56: =AVERAGE(J54:J68) -> 0.60930408
A57: =A55 -> Olkiluoto-3 (Finska) | I57: =I55 -> 3612.4221 | J57: =I57/($T$2*$U$2) -> 0.45650585 | K57: Max | L57: =MAX(I54:I68) -> 13835.566 | M57: Max | N57: =MAX(J54:J68) -> 1.7484161
A58: Barseback 2 (Švedska) | B58: 600 | C58: =$L$20*(B58/SUM($B$7:$B$12)) -> 469.8521 | D58: =C58*$Q$3 -> 459.98521 | E58: =D58*1000000 -> 4.5998521e+08 | F58: =FV($L$1,$L$53,,-E58,1) -> 7.5744315e+08 | G58: =PMT($L$3,$L$53,,-F58,1) -> 2019307 | H58: {=SUM(G58*(1+$L$3)^ROW(INDIRECT("1:"&$L$53)))} -> 7.5744315e+08 | I58: =G58/(SUM(B58)) -> 3365.5116 | J58: =I58/($T$2*$U$2) -> 0.42530349 | K58: Min distribucije | L58: =$L$38 -> 5099.6109 | M58: Min distribucije | N58: =$N$55 -> 0.42530349
A59: Forsmark 2 (Švedska) | B59: 1121 | C59: =$L$20*(B59/SUM($B$7:$B$12)) -> 877.84035 | D59: =C59*$Q$3 -> 859.4057 | E59: =D59*1000000 -> 8.594057e+08 | F59: =FV($L$1,$L$53,,-E59,1) -> 1.4151563e+09 | G59: =PMT($L$3,$L$53,,-F59,1) -> 3772738.5 | H59: {=SUM(G59*(1+$L$3)^ROW(INDIRECT("1:"&$L$53)))} -> 1.4151563e+09 | I59: =G59/(SUM(B59)) -> 3365.5116 | J59: =I59/($T$2*$U$2) -> 0.42530349 | K59: Max distribucije | L59: =$L57 -> 13835.566 | M59: Max distribucije | N59: =$N$57 -> 1.7484161
A60: Forsmark 3 (Švedska) | B60: 1172 | C60: =$L$20*(B60/SUM($B$7:$B$12)) -> 917.77777 | D60: =C60*$Q$3 -> 898.50444 | E60: =D60*1000000 -> 8.9850444e+08 | F60: =FV($L$1,$L$53,,-E60,1) -> 1.479539e+09 | G60: =PMT($L$3,$L$53,,-F60,1) -> 3944379.6 | H60: {=SUM(G60*(1+$L$3)^ROW(INDIRECT("1:"&$L$53)))} -> 1.479539e+09 | I60: =G60/(SUM(B60)) -> 3365.5116 | J60: =I60/($T$2*$U$2) -> 0.42530349
A61: Oskarshamn 3 (Švedska) | B61: 1400 | C61: =$L$20*(B61/SUM($B$7:$B$12)) -> 1096.3216 | D61: =C61*$Q$3 -> 1073.2988 | E61: =D61*1000000 -> 1.0732988e+09 | F61: =FV($L$1,$L$53,,-E61,1) -> 1.7673674e+09 | G61: =PMT($L$3,$L$53,,-F61,1) -> 4711716.3 | H61: {=SUM(G61*(1+$L$3)^ROW(INDIRECT("1:"&$L$53)))} -> 1.7673674e+09 | I61: =G61/(SUM(B61)) -> 3365.5116 | J61: =I61/($T$2*$U$2) -> 0.42530349 | K61: * povprečje treh vrednosti | L61: =AVERAGE((306+147),(317+172),(394+198)) -> 511.33333 | M61: ** Delitev moči NEK na dva dela
A62: Ringhals 3 (Švedska) | B62: 1081 | C62: =$L$20*(B62/SUM($B$7:$B$12)) -> 846.51687 | D62: =C62*$Q$3 -> 828.74002 | E62: =D62*1000000 -> 8.2874002e+08 | F62: =FV($L$1,$L$53,,-E62,1) -> 1.3646601e+09 | G62: =PMT($L$3,$L$53,,-F62,1) -> 3638118.1 | H62: {=SUM(G62*(1+$L$3)^ROW(INDIRECT("1:"&$L$53)))} -> 1.3646601e+09 | I62: =G62/(SUM(B62)) -> 3365.5116 | J62: =I62/($T$2*$U$2) -> 0.42530349
A63: Ringhals 4 (Švedska) | B63: 1130 | C63: =$L$20*(B63/SUM($B$7:$B$12)) -> 884.88813 | D63: =C63*$Q$3 -> 866.30548 | E63: =D63*1000000 -> 8.6630548e+08 | F63: =FV($L$1,$L$53,,-E63,1) -> 1.4265179e+09 | G63: =PMT($L$3,$L$53,,-F63,1) -> 3803028.1 | H63: {=SUM(G63*(1+$L$3)^ROW(INDIRECT("1:"&$L$53)))} -> 1.4265179e+09 | I63: =G63/(SUM(B63)) -> 3365.5116 | J63: =I63/($T$2*$U$2) -> 0.42530349
A64: JEK1 | B64: 696 | C64: =C13 -> 1845 (2024) | D64: =D13 -> 1845 | E64: =D64*1000000 -> 1845000000 | F64: =FV($L$1,$L$53,,-E64,1) -> 3.0381034e+09 | G64: =PMT($L$3,$L$53,,-F64,1) -> 8099437.3 | H64: {=SUM(G64*(1+$L$3)^ROW(INDIRECT("1:"&$L$53)))} -> 3.0381034e+09 | I64: =G64/(SUM(B64)) -> 11637.123 | J64: =I64/($S$2*$U$2) -> 1.4760429
A65: JEK2* | B65: =1250 -> 1250 | C65: 3227 (2024) | D65: =3227*$C$74 -> 1041.5861 | E65: =D65*1000000 -> 1.0415861e+09 | F65: =FV($S$3,$L$53,,-E65,1) -> 1.0415861e+09 | G65: =PMT($S$4,$L$53,,-F65,1) -> 4485050.7 | H65: {=SUM(G65*(1+$S$4)^ROW(INDIRECT("1:"&$L$53)))} -> 1.0415861e+09 | I65: =G65/(SUM(B65)) -> 3588.0405 | J65: =I65/($R$2*$U$2) -> 0.4404233
A66: JEK2* | B66: =1250 -> 1250 | C66: 3227 (2024) | D66: =3227*$C$74 -> 1041.5861 | E66: =D66*1000000 -> 1.0415861e+09 | F66: =FV($S$3,$L$53,,-E66,1) -> 1.0415861e+09 | G66: =PMT($S$4,$L$53,,-F66,1) -> 4485050.7 | H66: {=SUM(G66*(1+$S$4)^ROW(INDIRECT("1:"&$L$53)))} -> 1.0415861e+09 | I66: =G66/(SUM(B66)) -> 3588.0405 | J66: =I66/($R$2*$U$2) -> 0.4404233
A67: Gosgen (Švica) | B67: 1010 | C67: 4751 (2020) | D67: =4751*$N$3*$L$12 -> 3183.17 | E67: =D67*1000000 -> 3183170000 | F67: =FV($L$1,$L$53,,-E67,1) -> 5.2416257e+09 | G67: =PMT($L$3,$L$53,,-F67,1) -> 13973922 | H67: {=SUM(G67*(1+$L$3)^ROW(INDIRECT("1:"&$L$53)))} -> 5.2416257e+09 | I67: =G67/(SUM(B67)) -> 13835.566 | J67: =I67/($T$2*$U$2) -> 1.7484161
A68: Nova češka JE | I68: =F87 -> 5194.3137 | J68: =I68/($T$2*$U$2) -> 0.65641128
A70: GEN ENERGIJA
B71: 1000 | C71: 1250 | D71: 1650
A72: Odpadki | B72: =306+147 -> 453 | C72: =317+172 -> 489 | D72: =394+198 -> 592
A73: Razgradnja | B73: 820 | C73: 1026 | D73: 1354
A74: Delež odpadki | B74: =B72/SUM(B72:B73) -> 0.35585232 | C74: =C72/SUM(C72:C73) -> 0.32277228 | D74: =D72/SUM(D72:D73) -> 0.30421377
A75: Delež razgradnja | B75: =B73/SUM(B72:B73) -> 0.64414768 | C75: =C73/SUM(C72:C73) -> 0.67722772 | D75: =D73/SUM(D72:D73) -> 0.69578623
A76: Zbrana sredstva | B76: =2581*1000000 -> 2581000000 | C76: =3227*1000000 -> 3227000000 | D76: =4259*1000000 -> 4259000000
A77: Letno vplačilo | B77: =PMT(0.015,80,,-B76,1) -> 16651450 | C77: =PMT(0.015,80,,-C76,1) -> 20819151 | D77: =PMT(0.015,80,,-D76,1) -> 27477151
A78: Letno vplačilo/MW | B78: =B77/B71 -> 16651.45 | C78: =C77/C71 -> 16655.321 | D78: =D77/D71 -> 16652.819 | E78: Povprečje
A79: Odpadki | B79: =B78*B74 -> 5925.4571 | C79: =C78*C74 -> 5375.8759 | D79: =D78*D74 -> 5066.0168 | E79: =AVERAGE(B79:D79) -> 5455.7833
A80: Razgradnja | B80: =B78*B75 -> 10725.993 | C80: =C78*C75 -> 11279.445 | D80: =D78*D75 -> 11586.802 | E80: =AVERAGE(B80:D80) -> 11197.413
A82: Čehi - odpadki in decom | B82: 4 | C82: EUR/MWh | F82: 84 člen dopisa med podjetjem in EK
B83: 1 leto | C83: 60 | D83: 40 | E83: 80 | F83: 100
A84: Polna vrednost EUR/MW | B84: =B82*0.9*8760 -> 31536 | C84: {=SUM(B84*(1+$L$3)^ROW(INDIRECT("1:"&$C$83)))} -> 4012974 | G84: 90% cene, saj je padec od ene do druge JE | H84: 0.9
A85: Vrednost, ki odpade na odpadke | B85: =B84*AVERAGE(B74:D74) -> 10331.597 | C85: =C84*AVERAGE(B74:D74)*H84 -> 1183231.4
A86: Vrednost čez x let | C86: =FV($L$1,C83,,-C85,1) -> 1596001.9 | D86: =FV($L$1,D83,,-C85,1) -> 1444482.1 | E86: =FV($L$1,E83,,-C85,1) -> 1763415.4 | F86: =FV($L$1,F83,,-C85,1) -> 1948389.9
A87: Letno vplačilo | C87: =PMT($L$3,C83,,-C86,1) -> 12542.198 | D87: =PMT($L$3,D83,,-D86,1) -> 22147.376 | E87: =PMT($L$3,E83,,-E86,1) -> 7870.7138 | F87: =PMT($L$3,F83,,-F86,1) -> 5194.3137

Sheet Stroški razgradnje
A1: 40 LET | K1: Escalation rate - MZPP | L1: 0.005 | N1: Finančni podatki | Q1: JEK2 - Capacity factor - GEN-E | R1: NEK - Capacity factor - GEN-E | S1: Capacity faktor - MZPP | T1: Ur v letu dni
A2: Jedrska elektrarna | B2: Moč reaktorja (MW) | C2: Cena razgradnje 2020-2023 (mio. €) | D2: Cena razgradnje 2024 (mio. €) | E2: Cena razgradnje 2024 [EUR] | F2: Cena razgradnje povečana za escalation rate (y + 40) | G2: Letno plačilo, da v 40 letih pridemo do končne investicijske vrednosti | H2: Preverba, da prideš do istih cifer | I2: Strošek (€/MW/leto) | J2: Strošek (€/MWh) | K2: Povprečje let | L2: 40 | N2: Inflacija iz leta 2020 do sredine 2024 | O2: Inflacija iz leta 2021 do sredine 2024 | P2: Inflacija iz leta 2023 do sredine 2024 | Q2: 0.93 | R2: ='Stroški odpadkov'!$S$2 -> 0.9 | S2: ='Capacity factor'!$B$5 -> 0.90333333 | T2: 8760
A3: Fessenheim 1,2 (Francija) | B3: 1840 | C3: 808 (2021) | D3: =808*O3 -> 910.616 | E3: =D3*1000000 -> 910616000 | F3: =FV($L$1,$L$2,,-E3,1) -> 1.1116748e+09 | G3: =PMT($L$3,$L$2,,-F3,1) -> 17044641 | H3: {=SUM(G3*(1+$L$3)^ROW(INDIRECT("1:"&$L$2)))} -> 1.1116748e+09 | I3: =G3/B3 -> 9263.3919 | J3: =I3/($T$2*$S$2) -> 1.1706253 | K3: Interest rate - MZPP | L3: 0.0225 | N3: =1.34 -> 1.34 | O3: =1.127 -> 1.127 | P3: 1.002 | Q3: Escalation rate - GEN | R3: 0
A4: Chooz-A (Francija) | B4: 320 | C4: 280 (2021) | D4: =280*O3 -> 315.56 | E4: =D4*1000000 -> 315560000 | F4: =FV($L$1,$L$2,,-E4,1) -> 3.8523383e+08 | G4: =PMT($L$3,$L$2,,-F4,1) -> 5906558.8 | H4: {=SUM(G4*(1+$L$3)^ROW(INDIRECT("1:"&$L$2)))} -> 3.8523383e+08 | I4: =G4/B4 -> 18457.996 | J4: =I4/($T$2*$S$2) -> 2.3325578 | Q4: Interest rate - GEN | R4: =0.015 -> 0.015
A5: Super-Phenix (Francija) | B5: 1242 | C5: 520.5 (2021) | D5: =520.5*O3 -> 586.6035 | E5: =D5*1000000 -> 586603500 | F5: =FV($L$1,$L$2,,-E5,1) -> 7.1612217e+08 | G5: =PMT($L$3,$L$2,,-F5,1) -> 10979871 | H5: {=SUM(G5*(1+$L$3)^ROW(INDIRECT("1:"&$L$2)))} -> 7.1612217e+08 | I5: =G5/B5 -> 8840.4758 | J5: =I5/($T$2*$S$2) -> 1.1171809 | K5: Strošek (€/MW/leto) | M5: Strošek (€/MWh)
A6: Obrigheim (Nemčija) | B6: 340 | C6: 630.4 (2020) | D6: =630.4*N3 -> 844.736 | E6: =D6*1000000 -> 844736000 | F6: =FV($L$1,$L$2,,-E6,1) -> 1.0312488e+09 | G6: =PMT($L$3,$L$2,,-F6,1) -> 15811519 | H6: {=SUM(G6*(1+$L$3)^ROW(INDIRECT("1:"&$L$2)))} -> 1.0312488e+09 | I6: =G6/B6 -> 46504.467 | J6: =I6/($T$2*$S$2) -> 5.8768219 | K6: Min | L6: =MIN(I3:I13) -> 8840.4758 | M6: Min | N6: =MIN(J3:J14) -> 1.1171809
A7: Muelheim-Kaerlich (Nemčija) | B7: 1219 | C7: 761.7 (2020) | D7: =761.7*N3 -> 1020.678 | E7: =D7*1000000 -> 1.020678e+09 | F7: =FV($L$1,$L$2,,-E7,1) -> 1.2460378e+09 | G7: =PMT($L$3,$L$2,,-F7,1) -> 19104749 | H7: {=SUM(G7*(1+$L$3)^ROW(INDIRECT("1:"&$L$2)))} -> 1.2460378e+09 | I7: =G7/B7 -> 15672.477 | J7: =I7/($T$2*$S$2) -> 1.9805485 | K7: Average | L7: =AVERAGE(I3:I13) -> 25490.7 | M7: Average | N7: =AVERAGE(J3:J14) -> 3.4129571
A8: Greifswald 1-5 (Nemčija) | B8: =5*408 -> 2040 | C8: 4202.4 (2020) | D8: =4202.4*N3 -> 5631.216 | E8: =D8*1000000 -> 5.631216e+09 | F8: =FV($L$1,$L$2,,-E8,1) -> 6.874556e+09 | G8: =PMT($L$3,$L$2,,-F8,1) -> 1.0540344e+08 | H8: {=SUM(G8*(1+$L$3)^ROW(INDIRECT("1:"&$L$2)))} -> 6.874556e+09 | I8: =G8/B8 -> 51668.351 | J8: =I8/($T$2*$S$2) -> 6.5293878 | K8: Max | L8: =MAX(I3:I13) -> 51668.351 | M8: Max | N8: =MAX(J3:J14) -> 6.5293878
A9: Beznau 1, 2 (Švica) | B9: =2*365 -> 730 | C9: 887,5 (2020) | D9: =887.5*N3 -> 1189.25 | E9: =D9*1000000 -> 1189250000 | F9: =FV($L$1,$L$2,,-E9,1) -> 1.4518295e+09 | G9: =PMT($L$3,$L$2,,-F9,1) -> 22260030 | H9: {=SUM(G9*(1+$L$3)^ROW(INDIRECT("1:"&$L$2)))} -> 1.4518295e+09 | I9: =G9/B9 -> 30493.192 | J9: =I9/($T$2*$S$2) -> 3.853459 | K9: Min distribucije | L9: =$L$6 -> 8840.4758 | M9: Min distribucije | N9: =$N$6 -> 1.1171809
A10: Gosgen (Švica) | B10: 1010 | C10: 835.2 (2020) | D10: =835.2*N3 -> 1119.168 | E10: =D10*1000000 -> 1.119168e+09 | F10: =FV($L$1,$L$2,,-E10,1) -> 1.3662738e+09 | G10: =PMT($L$3,$L$2,,-F10,1) -> 20948256 | H10: {=SUM(G10*(1+$L$3)^ROW(INDIRECT("1:"&$L$2)))} -> 1.3662738e+09 | I10: =G10/B10 -> 20740.847 | J10: =I10/($T$2*$S$2) -> 2.6210442 | K10: Max distribucije | L10: =$L$8 -> 51668.351 | M10: Max distribucije | N10: =$N$8 -> 6.5293878
A11: JEK1 | B11: 696 | C11: 568 (2024) | D11: =568 -> 568 | E11: =D11*1000000 -> 568000000 | F11: =FV($L$1,$L$2,,-E11,1) -> 6.9341113e+08 | G11: =PMT($L$3,$L$2,,-F11,1) -> 10631656 | H11: {=SUM(G11*(1+$L$3)^ROW(INDIRECT("1:"&$L$2)))} -> 6.9341113e+08 | I11: =G11/B11 -> 15275.368 | J11: =I11/($T$2*$R$2) -> 1.937515
A12: JEK2* | B12: =1250 -> 1250 | C12: 3227 (2024) | D12: =3227*$C$69 -> 2185.4139 | E12: =D12*1000000 -> 2.1854139e+09 | F12: =FV($R$3,$L$2,,-E12,1) -> 2.1854139e+09 | G12: =PMT($R$4,$L$2,,-F12,1) -> 39675708 | H12: {=SUM(G12*(1+$R$4)^ROW(INDIRECT("1:"&$L$2)))} -> 2.1854139e+09 | I12: =G12/B12 -> 31740.566 | J12: =I12/($T$2*$Q$2) -> 3.8960778
A13: JEK2* | B13: =1250 -> 1250 | C13: 3227 (2024) | D13: =3227*$C$69 -> 2185.4139 | E13: =D13*1000000 -> 2.1854139e+09 | F13: =FV($R$3,$L$2,,-E13,1) -> 2.1854139e+09 | G13: =PMT($R$4,$L$2,,-F13,1) -> 39675708 | H13: {=SUM(G13*(1+$R$4)^ROW(INDIRECT("1:"&$L$2)))} -> 2.1854139e+09 | I13: =G13/B13 -> 31740.566 | J13: =I13/($T$2*$Q$2) -> 3.8960778
A14: Čehi | I14: =$D$81 -> 45454.918 | J14: =I14/($T$2*$S$2) -> 5.7441892 | K14: Leta | L14: 60
A15: 60 LET
A16: =A2 -> Jedrska elektrarna | B16: =B2 -> Moč reaktorja (MW) | C16: =C2 -> Cena razgradnje 2020-2023 (mio. €) | D16: =D2 -> Cena razgradnje 2024 (mio. €) | E16: =E2 -> Cena razgradnje 2024 [EUR] | F16: Cena razgradnje povečana za escalation rate (y + 60) | G16: Letno plačilo, da v 60 letih pridemo do končne investicijske vrednosti | H16: Preverba, da prideš do istih cifer | I16: Strošek (€/MW/leto) | J16: Strošek (€/MWh)
A17: =A3 -> Fessenheim 1,2 (Francija) | B17: =B3 -> 1840 | C17: =C3 -> 808 (2021) | D17: =D3 -> 910.616 | E17: =E3 -> 910616000 | F17: =FV($L$1,$L$14,,-E17,1) -> 1.2282845e+09 | G17: =PMT($L$3,$L$14,,-F17,1) -> 9652487.5 | H17: {=SUM(G17*(1+$L$3)^ROW(INDIRECT("1:"&$L$14)))} -> 1.2282845e+09 | I17: =G17/B17 -> 5245.9171 | J17: =I17/($T$2*$S$2) -> 0.66293246
A18: =A4 -> Chooz-A (Francija) | B18: =B4 -> 320 | C18: =C4 -> 280 (2021) | D18: =D4 -> 315.56 | E18: =E4 -> 315560000 | F18: =FV($L$1,$L$14,,-E18,1) -> 4.2564315e+08 | G18: =PMT($L$3,$L$14,,-F18,1) -> 3344921.4 | H18: {=SUM(G18*(1+$L$3)^ROW(INDIRECT("1:"&$L$14)))} -> 4.2564315e+08 | I18: =G18/B18 -> 10452.879 | J18: =I18/($T$2*$S$2) -> 1.3209421
A19: =A5 -> Super-Phenix (Francija) | B19: =B5 -> 1242 | C19: =C5 -> 520.5 (2021) | D19: =D5 -> 586.6035 | E19: =E5 -> 586603500 | F19: =FV($L$1,$L$14,,-E19,1) -> 7.9124022e+08 | G19: =PMT($L$3,$L$14,,-F19,1) -> 6217970 | H19: {=SUM(G19*(1+$L$3)^ROW(INDIRECT("1:"&$L$14)))} -> 7.9124022e+08 | I19: =G19/B19 -> 5006.417 | J19: =I19/($T$2*$S$2) -> 0.63266656 | K19: Strošek (€/MW/leto) | M19: Strošek (€/MWh)
A20: =A6 -> Obrigheim (Nemčija) | B20: =B6 -> 340 | C20: =C6 -> 630.4 (2020) | D20: =D6 -> 844.736 | E20: =E6 -> 844736000 | F20: =FV($L$1,$L$14,,-E20,1) -> 1.1394223e+09 | G20: =PMT($L$3,$L$14,,-F20,1) -> 8954162.5 | H20: {=SUM(G20*(1+$L$3)^ROW(INDIRECT("1:"&$L$14)))} -> 1.1394223e+09 | I20: =G20/B20 -> 26335.772 | J20: =I20/($T$2*$S$2) -> 3.3280812 | K20: Min | L20: =MIN(I17:I28) -> 5006.417 | M20: Min | N20: =MIN(J17:J28) -> 0.63266656
A21: =A7 -> Muelheim-Kaerlich (Nemčija) | B21: =B7 -> 1219 | C21: =C7 -> 761.7 (2020) | D21: =D7 -> 1020.678 | E21: =E7 -> 1.020678e+09 | F21: =FV($L$1,$L$14,,-E21,1) -> 1.3767417e+09 | G21: =PMT($L$3,$L$14,,-F21,1) -> 10819140 | H21: {=SUM(G21*(1+$L$3)^ROW(INDIRECT("1:"&$L$14)))} -> 1.3767417e+09 | I21: =G21/B21 -> 8875.4221 | J21: =I21/($T$2*$S$2) -> 1.1215971 | K21: Average | L21: =AVERAGE(I17:I28) -> 15365.654 | M21: Average | N21: =AVERAGE(J17:J28) -> 1.9313006
A22: =A8 -> Greifswald 1-5 (Nemčija) | B22: =B8 -> 2040 | C22: =C8 -> 4202.4 (2020) | D22: =D8 -> 5631.216 | E22: =E8 -> 5.631216e+09 | F22: =FV($L$1,$L$14,,-E22,1) -> 7.5956666e+09 | G22: =PMT($L$3,$L$14,,-F22,1) -> 59690629 | H22: {=SUM(G22*(1+$L$3)^ROW(INDIRECT("1:"&$L$14)))} -> 7.5956666e+09 | I22: =G22/B22 -> 29260.112 | J22: =I22/($T$2*$S$2) -> 3.6976334 | K22: Max | L22: =MAX(I17:I28) -> 29260.112 | M22: Max | N22: =MAX(J17:J28) -> 3.6976334
A23: =A9 -> Beznau 1, 2 (Švica) | B23: =B9 -> 730 | C23: =C9 -> 887,5 (2020) | D23: =D9 -> 1189.25 | E23: =E9 -> 1189250000 | F23: =FV($L$1,$L$14,,-E23,1) -> 1.60412e+09 | G23: =PMT($L$3,$L$14,,-F23,1) -> 12605995 | H23: {=SUM(G23*(1+$L$3)^ROW(INDIRECT("1:"&$L$14)))} -> 1.60412e+09 | I23: =G23/B23 -> 17268.486 | J23: =I23/($T$2*$S$2) -> 2.1822381 | K23: Min distribucije | L23: =$L$20 -> 5006.417 | M23: Min distribucije | N23: =$N$20 -> 0.63266656
A24: =A10 -> Gosgen (Švica) | B24: =B10 -> 1010 | C24: =C10 -> 835.2 (2020) | D24: =D10 -> 1119.168 | E24: =E10 -> 1.119168e+09 | F24: =FV($L$1,$L$14,,-E24,1) -> 1.5095899e+09 | G24: =PMT($L$3,$L$14,,-F24,1) -> 11863129 | H24: {=SUM(G24*(1+$L$3)^ROW(INDIRECT("1:"&$L$14)))} -> 1.5095899e+09 | I24: =G24/B24 -> 11745.672 | J24: =I24/($T$2*$S$2) -> 1.4843138 | K24: Max distribucije | L24: =$L$22 -> 29260.112 | M24: Max distribucije | N24: =$N$22 -> 3.6976334
A25: JEK1 | B25: 696 | C25: =C11 -> 568 (2024) | D25: =D11 -> 568 | E25: =D25*1000000 -> 568000000 | F25: =FV($L$1,$L$14,,-E25,1) -> 7.6614689e+08 | G25: =PMT($L$3,$L$14,,-F25,1) -> 6020773.7 | H25: {=SUM(G25*(1+$L$3)^ROW(INDIRECT("1:"&$L$14)))} -> 7.6614689e+08 | I25: =G25/B25 -> 8650.537 | J25: =I25/($T$2*$R$2) -> 1.0972269
A26: JEK2* | B26: =1250 -> 1250 | C26: 3227 (2024) | D26: =3227*$C$69 -> 2185.4139 | E26: =D26*1000000 -> 2.1854139e+09 | F26: =FV($R$3,$L$14,,-E26,1) -> 2.1854139e+09 | G26: =PMT($R$4,$L$14,,-F26,1) -> 22378266 | H26: {=SUM(G26*(1+$R$4)^ROW(INDIRECT("1:"&$L$14)))} -> 2.1854139e+09 | I26: =G26/B26 -> 17902.613 | J26: =I26/($T$2*$Q$2) -> 2.1975025
A27: JEK2* | B27: =1250 -> 1250 | C27: 3227 (2024) | D27: =3227*$C$69 -> 2185.4139 | E27: =D27*1000000 -> 2.1854139e+09 | F27: =FV($R$3,$L$14,,-E27,1) -> 2.1854139e+09 | G27: =PMT($R$4,$L$14,,-F27,1) -> 22378266 | H27: {=SUM(G27*(1+$R$4)^ROW(INDIRECT("1:"&$L$14)))} -> 2.1854139e+09 | I27: =G27/B27 -> 17902.613 | J27: =I27/($T$2*$Q$2) -> 2.1975025
A28: =$A$14 -> Čehi | I28: =$C$81 -> 25741.406 | J28: =I28/($T$2*$S$2) -> 3.2529705 | K28: Leta | L28: 80
A29: 80 LET
A30: =A16 -> Jedrska elektrarna | B30: =B16 -> Moč reaktorja (MW) | C30: =C16 -> Cena razgradnje 2020-2023 (mio. €) | D30: =D16 -> Cena razgradnje 2024 (mio. €) | E30: =E16 -> Cena razgradnje 2024 [EUR] | F30: Cena razgradnje povečana za escalation rate (y + 80) | G30: Letno plačilo, da v 80 letih pridemo do končne investicijske vrednosti | H30: Preverba, da prideš do istih cifer | I30: Strošek (€/MW/leto) | J30: Strošek (€/MWh)
A31: =A17 -> Fessenheim 1,2 (Francija) | B31: =B17 -> 1840 | C31: =C17 -> 808 (2021) | D31: =D17 -> 910.616 | E31: =E17 -> 910616000 | F31: =FV($L$1,$L$28,,-E31,1) -> 1.3571261e+09 | G31: =PMT($L$3,$L$28,,-F31,1) -> 6057308.6 | H31: {=SUM(G31*(1+$L$3)^ROW(INDIRECT("1:"&$L$28)))} -> 1.3571261e+09 | I31: =G31/B31 -> 3292.0155 | J31: =I31/($T$2*$S$2) -> 0.41601571
A32: =A18 -> Chooz-A (Francija) | B32: =B18 -> 320 | C32: =C18 -> 280 (2021) | D32: =D18 -> 315.56 | E32: =E18 -> 315560000 | F32: =FV($L$1,$L$28,,-E32,1) -> 4.7029124e+08 | G32: =PMT($L$3,$L$28,,-F32,1) -> 2099067.3 | H32: {=SUM(G32*(1+$L$3)^ROW(INDIRECT("1:"&$L$28)))} -> 4.7029124e+08 | I32: =G32/B32 -> 6559.5854 | J32: =I32/($T$2*$S$2) -> 0.8289422 | K32: Strošek (€/MW/leto) | M32: Strošek (€/MWh)
A33: =A19 -> Super-Phenix (Francija) | B33: =B19 -> 1242 | C33: =C19 -> 520.5 (2021) | D33: =D19 -> 586.6035 | E33: =E19 -> 586603500 | F33: =FV($L$1,$L$28,,-E33,1) -> 8.7423782e+08 | G33: =PMT($L$3,$L$28,,-F33,1) -> 3902016.2 | H33: {=SUM(G33*(1+$L$3)^ROW(INDIRECT("1:"&$L$28)))} -> 8.7423782e+08 | I33: =G33/B33 -> 3141.72 | J33: =I33/($T$2*$S$2) -> 0.3970227 | K33: Min | L33: =MIN(I31:I42) -> 3141.72 | M33: Min | N33: =MIN(J31:J42) -> 0.3970227
A34: =A20 -> Obrigheim (Nemčija) | B34: =B20 -> 340 | C34: =C20 -> 630.4 (2020) | D34: =D20 -> 844.736 | E34: =E20 -> 844736000 | F34: =FV($L$1,$L$28,,-E34,1) -> 1.2589426e+09 | G34: =PMT($L$3,$L$28,,-F34,1) -> 5619082.7 | H34: {=SUM(G34*(1+$L$3)^ROW(INDIRECT("1:"&$L$28)))} -> 1.2589426e+09 | I34: =G34/B34 -> 16526.714 | J34: =I34/($T$2*$S$2) -> 2.0884995 | K34: Average | L34: =AVERAGE(I31:I42) -> 9650.0186 | M34: Average | N34: =AVERAGE(J31:J42) -> 1.207872
A35: =A21 -> Muelheim-Kaerlich (Nemčija) | B35: =B21 -> 1219 | C35: =C21 -> 761.7 (2020) | D35: =D21 -> 1020.678 | E35: =E21 -> 1.020678e+09 | F35: =FV($L$1,$L$28,,-E35,1) -> 1.5211558e+09 | G35: =PMT($L$3,$L$28,,-F35,1) -> 6789427.8 | H35: {=SUM(G35*(1+$L$3)^ROW(INDIRECT("1:"&$L$28)))} -> 1.5211558e+09 | I35: =G35/B35 -> 5569.6701 | J35: =I35/($T$2*$S$2) -> 0.70384549 | K35: Max | L35: =MAX(I31:I42) -> 18361.85 | M35: Max | N35: =MAX(J31:J42) -> 2.3204077
A36: =A22 -> Greifswald 1-5 (Nemčija) | B36: =B22 -> 2040 | C36: =C22 -> 4202.4 (2020) | D36: =D22 -> 5631.216 | E36: =E22 -> 5.631216e+09 | F36: =FV($L$1,$L$28,,-E36,1) -> 8.3924184e+09 | G36: =PMT($L$3,$L$28,,-F36,1) -> 37458175 | H36: {=SUM(G36*(1+$L$3)^ROW(INDIRECT("1:"&$L$28)))} -> 8.3924184e+09 | I36: =G36/B36 -> 18361.85 | J36: =I36/($T$2*$S$2) -> 2.3204077 | K36: Min distribucije | L36: =$L$33 -> 3141.72 | M36: Min distribucije | N36: =$N$33 -> 0.3970227
A37: =A23 -> Beznau 1, 2 (Švica) | B37: =B23 -> 730 | C37: =C23 -> 887,5 (2020) | D37: =D23 -> 1189.25 | E37: =E23 -> 1189250000 | F37: =FV($L$1,$L$28,,-E37,1) -> 1.7723851e+09 | G37: =PMT($L$3,$L$28,,-F37,1) -> 7910748.6 | H37: {=SUM(G37*(1+$L$3)^ROW(INDIRECT("1:"&$L$28)))} -> 1.7723851e+09 | I37: =G37/B37 -> 10836.642 | J37: =I37/($T$2*$S$2) -> 1.3694387 | K37: Max distribucije | L37: =$L$35 -> 18361.85 | M37: Max distribucije | N37: =$N$35 -> 2.3204077
A38: =A24 -> Gosgen (Švica) | B38: =B24 -> 1010 | C38: =C24 -> 835.2 (2020) | D38: =D24 -> 1119.168 | E38: =E24 -> 1.119168e+09 | F38: =FV($L$1,$L$28,,-E38,1) -> 1.6679392e+09 | G38: =PMT($L$3,$L$28,,-F38,1) -> 7444571.5 | H38: {=SUM(G38*(1+$L$3)^ROW(INDIRECT("1:"&$L$28)))} -> 1.6679392e+09 | I38: =G38/B38 -> 7370.8629 | J38: =I38/($T$2*$S$2) -> 0.93146425
A39: JEK1 | B39: 696 | C39: =C11 -> 568 (2024) | D39: =D11 -> 568 | E39: =D39*1000000 -> 568000000 | F39: =FV($L$1,$L$28,,-E39,1) -> 8.4651231e+08 | G39: =PMT($L$3,$L$28,,-F39,1) -> 3778268 | H39: {=SUM(G39*(1+$L$3)^ROW(INDIRECT("1:"&$L$28)))} -> 8.4651231e+08 | I39: =G39/B39 -> 5428.546 | J39: =I39/($T$2*$R$2) -> 0.68855225
A40: JEK2* | B40: =1250 -> 1250 | C40: 3227 (2024) | D40: =3227*$C$69 -> 2185.4139 | E40: =D40*1000000 -> 2.1854139e+09 | F40: =FV($R$3,$L$28,,-E40,1) -> 2.1854139e+09 | G40: =PMT($R$4,$L$28,,-F40,1) -> 14099306 | H40: {=SUM(G40*(1+$R$4)^ROW(INDIRECT("1:"&$L$28)))} -> 2.1854139e+09 | I40: =G40/B40 -> 11279.445 | J40: =2*$C$69 -> 1.3544554
A41: JEK2* | B41: =1250 -> 1250 | C41: 3227 (2024) | D41: =3227*$C$69 -> 2185.4139 | E41: =D41*1000000 -> 2.1854139e+09 | F41: =FV($R$3,$L$28,,-E41,1) -> 2.1854139e+09 | G41: =PMT($R$4,$L$28,,-F41,1) -> 14099306 | H41: {=SUM(G41*(1+$R$4)^ROW(INDIRECT("1:"&$L$28)))} -> 2.1854139e+09 | I41: =G41/B41 -> 11279.445 | J41: =2*$C$69 -> 1.3544554 | K41: Leta | L41: 100
A42: =A28 -> Čehi | I42: =$E$81 -> 16153.726 | J42: =I42/($T$2*$S$2) -> 2.0413646
A43: 100 LET
A44: =A30 -> Jedrska elektrarna | B44: =B30 -> Moč reaktorja (MW) | C44: =C30 -> Cena razgradnje 2020-2023 (mio. €) | D44: =D30 -> Cena razgradnje 2024 (mio. €) | E44: =E30 -> Cena razgradnje 2024 [EUR] | F44: Cena razgradnje povečana za escalation rate (y + 100) | G44: Letno plačilo, da v 100 letih pridemo do končne investicijske vrednosti | H44: Preverba, da prideš do istih cifer | I44: Strošek (€/MW/leto) | J44: Strošek (€/MWh)
A45: =A31 -> Fessenheim 1,2 (Francija) | B45: =B31 -> 1840 | C45: =C31 -> 808 (2021) | D45: =D31 -> 910.616 | E45: =E31 -> 910616000 | F45: =FV($L$1,$L41,,-E45,1) -> 1.4994827e+09 | G45: =PMT($L$3,$L$41,,-F45,1) -> 3997548.6 | H45: {=SUM(G45*(1+$L$3)^ROW(INDIRECT("1:"&$L$41)))} -> 1.4994827e+09 | I45: =G45/B45 -> 2172.5808 | J45: =I45/($T$2*$S$2) -> 0.27455148 | K45: Strošek (€/MW/leto) | M45: Strošek (€/MWh)
A46: =A32 -> Chooz-A (Francija) | B46: =B32 -> 320 | C46: =C32 -> 280 (2021) | D46: =D32 -> 315.56 | E46: =E32 -> 315560000 | F46: =FV($L$1,$L$41,,-E46,1) -> 5.1962271e+08 | G46: =PMT($L$3,$L$41,,-F46,1) -> 1385289.1 | H46: {=SUM(G46*(1+$L$3)^ROW(INDIRECT("1:"&$L$41)))} -> 5.1962271e+08 | I46: =G46/B46 -> 4329.0285 | J46: =I46/($T$2*$S$2) -> 0.54706421 | K46: Min | L46: =MIN(I45:I56) -> 2073.3925 | M46: Min | N46: =MIN(J45:J56) -> 0.26201695
A47: =A33 -> Super-Phenix (Francija) | B47: =B33 -> 1242 | C47: =C33 -> 520.5 (2021) | D47: =D33 -> 586.6035 | E47: =E33 -> 586603500 | F47: =FV($L$1,$L$41,,-E47,1) -> 9.659415e+08 | G47: =PMT($L$3,$L$41,,-F47,1) -> 2575153.5 | H47: {=SUM(G47*(1+$L$3)^ROW(INDIRECT("1:"&$L$41)))} -> 9.659415e+08 | I47: =G47/B47 -> 2073.3925 | J47: =I47/($T$2*$S$2) -> 0.26201695 | K47: Average | L47: =AVERAGE(I45:I56) -> 6382.634 | M47: Average | N47: =AVERAGE(J45:J56) -> 0.80217387
A48: =A34 -> Obrigheim (Nemčija) | B48: =B34 -> 340 | C48: =C34 -> 630.4 (2020) | D48: =D34 -> 844.736 | E48: =E34 -> 844736000 | F48: =FV($L$1,$L$41,,-E48,1) -> 1.3910002e+09 | G48: =PMT($L$3,$L$41,,-F48,1) -> 3708339.4 | H48: {=SUM(G48*(1+$L$3)^ROW(INDIRECT("1:"&$L$41)))} -> 1.3910002e+09 | I48: =G48/B48 -> 10906.881 | J48: =I48/($T$2*$S$2) -> 1.3783148 | K48: Max | L48: =MAX(I45:I56) -> 12117.987 | M48: Max | N48: =MAX(J45:J56) -> 1.5313637
A49: =A35 -> Muelheim-Kaerlich (Nemčija) | B49: =B35 -> 1219 | C49: =C35 -> 761.7 (2020) | D49: =D35 -> 1020.678 | E49: =E35 -> 1.020678e+09 | F49: =FV($L$1,$L$41,,-E49,1) -> 1.6807183e+09 | G49: =PMT($L$3,$L$41,,-F49,1) -> 4480714.1 | H49: {=SUM(G49*(1+$L$3)^ROW(INDIRECT("1:"&$L$41)))} -> 1.6807183e+09 | I49: =G49/B49 -> 3675.7293 | J49: =I49/($T$2*$S$2) -> 0.46450606 | K49: Min distribucije | L49: =$L$46 -> 2073.3925 | M49: Min distribucije | N49: =$N$46 -> 0.26201695
A50: =A36 -> Greifswald 1-5 (Nemčija) | B50: =B36 -> 2040 | C50: =C36 -> 4202.4 (2020) | D50: =D36 -> 5631.216 | E50: =E36 -> 5.631216e+09 | F50: =FV($L$1,$L$41,,-E50,1) -> 9.272746e+09 | G50: =PMT($L$3,$L$41,,-F50,1) -> 24720694 | H50: {=SUM(G50*(1+$L$3)^ROW(INDIRECT("1:"&$L$41)))} -> 9.272746e+09 | I50: =G50/B50 -> 12117.987 | J50: =I50/($T$2*$S$2) -> 1.5313637 | K50: Max distribucije | L50: =$L$48 -> 12117.987 | M50: Max distribucije | N50: =$N$48 -> 1.5313637
A51: =A37 -> Beznau 1, 2 (Švica) | B51: =B37 -> 730 | C51: =C37 -> 887,5 (2020) | D51: =D37 -> 1189.25 | E51: =E37 -> 1189250000 | F51: =FV($L$1,$L$41,,-E51,1) -> 1.9583005e+09 | G51: =PMT($L$3,$L$41,,-F51,1) -> 5220734.8 | H51: {=SUM(G51*(1+$L$3)^ROW(INDIRECT("1:"&$L$41)))} -> 1.9583005e+09 | I51: =G51/B51 -> 7151.6916 | J51: =I51/($T$2*$S$2) -> 0.90376732
A52: =A38 -> Gosgen (Švica) | B52: =B38 -> 1010 | C52: =C38 -> 835.2 (2020) | D52: =D38 -> 1119.168 | E52: =E38 -> 1.119168e+09 | F52: =FV($L$1,$L$41,,-E52,1) -> 1.8428987e+09 | G52: =PMT($L$3,$L$41,,-F52,1) -> 4913079.1 | H52: {=SUM(G52*(1+$L$3)^ROW(INDIRECT("1:"&$L$41)))} -> 1.8428987e+09 | I52: =G52/B52 -> 4864.4348 | J52: =I52/($T$2*$S$2) -> 0.61472411
A53: JEK1 | B53: 696 | C53: =C11 -> 568 (2024) | D53: =D11 -> 568 | E53: =D53*1000000 -> 568000000 | F53: =FV($L$1,$L$41,,-E53,1) -> 9.353077e+08 | G53: =PMT($L$3,$L$41,,-F53,1) -> 2493485.3 | H53: {=SUM(G53*(1+$L$3)^ROW(INDIRECT("1:"&$L$41)))} -> 9.353077e+08 | I53: =G53/B53 -> 3582.5938 | J53: =I53/($T$2*$R$2) -> 0.45441322
A54: JEK2* | B54: =1250 -> 1250 | C54: 3227 (2024) | D54: =3227*$C$69 -> 2185.4139 | E54: =D54*1000000 -> 2.1854139e+09 | F54: =FV($R$3,$L$41,,-E54,1) -> 2.1854139e+09 | G54: =PMT($R$4,$L$41,,-F54,1) -> 9410351.7 | H54: {=SUM(G54*(1+$R$4)^ROW(INDIRECT("1:"&$L$41)))} -> 2.1854139e+09 | I54: =G54/B54 -> 7528.2814 | J54: =I54/($T$2*$Q$2) -> 0.92407833
A55: JEK2* | B55: =1250 -> 1250 | C55: 3227 (2024) | D55: =3227*$C$69 -> 2185.4139 | E55: =D55*1000000 -> 2.1854139e+09 | F55: =FV($R$3,$L$41,,-E55,1) -> 2.1854139e+09 | G55: =PMT($R$4,$L$41,,-F55,1) -> 9410351.7 | H55: {=SUM(G55*(1+$R$4)^ROW(INDIRECT("1:"&$L$41)))} -> 2.1854139e+09 | I55: =G55/B55 -> 7528.2814 | J55: =I55/($T$2*$Q$2) -> 0.92407833
A56: =A42 -> Čehi | I56: =$F$81 -> 10660.726 | J56: =I56/($T$2*$S$2) -> 1.3472079
A64: GEN ENERGIJA
B65: 1000 | C65: 1250 | D65: 1650
A66: Odpadki | B66: =306+147 -> 453 | C66: =317+172 -> 489 | D66: =394+198 -> 592
A67: Razgradnja | B67: 820 | C67: 1026 | D67: 1354
A68: Delež odpadki | B68: =B66/SUM(B66:B67) -> 0.35585232 | C68: =C66/SUM(C66:C67) -> 0.32277228 | D68: =D66/SUM(D66:D67) -> 0.30421377
A69: Delež razgradnja | B69: =B67/SUM(B66:B67) -> 0.64414768 | C69: =C67/SUM(C66:C67) -> 0.67722772 | D69: =D67/SUM(D66:D67) -> 0.69578623
A70: Zbrana sredstva | B70: =2581*1000000 -> 2581000000 | C70: =3227*1000000 -> 3227000000 | D70: =4259*1000000 -> 4259000000
A71: Letno vplačilo | B71: =PMT(0.015,80,,-B70,1) -> 16651450 | C71: =PMT(0.015,80,,-C70,1) -> 20819151 | D71: =PMT(0.015,80,,-D70,1) -> 27477151
A72: Letno vplačilo/MW | B72: =B71/B65 -> 16651.45 | C72: =C71/C65 -> 16655.321 | D72: =D71/D65 -> 16652.819 | E72: Povprečje
A73: Odpadki | B73: =B72*B68 -> 5925.4571 | C73: =C72*C68 -> 5375.8759 | D73: =D72*D68 -> 5066.0168 | E73: =AVERAGE(B73:D73) -> 5455.7833
A74: Razgradnja | B74: =B72*B69 -> 10725.993 | C74: =C72*C69 -> 11279.445 | D74: =D72*D69 -> 11586.802 | E74: =AVERAGE(B74:D74) -> 11197.413
A76: Čehi - odpadki in decom | B76: 4 | C76: EUR/MWh | F76: 84 člen dopisa med podjetjem in EK
B77: 1 leto | C77: 60 | D77: 40 | E77: 80 | F77: 100 | G77: predpostavljajo 60 let življ dobe
A78: Polna vrednost EUR/MW | B78: =B76*0.9*8760 -> 31536 | C78: {=SUM(B78*(1+$L$3)^ROW(INDIRECT("1:"&$C$77)))} -> 4012974 | G78: oni predpostavljajo 90% CF | H78: 90% cene, saj je padec od ene do druge JE | I78: 0.9
A79: Vrednost, ki odpade na razgradnjo | B79: =B78*AVERAGE(B69:D69) -> 21204.403 | C79: =C78*AVERAGE(B69:D69)*I78 -> 2428445.1
A80: Vrednost čez x let | C80: =FV($L$1,C77,,-C79,1) -> 3275608.6 | D80: =FV($L$1,D77,,-C79,1) -> 2964631.8 | E80: =FV($L$1,E77,,-C79,1) -> 3619205.4 | F80: =FV($L$1,F77,,-C79,1) -> 3998844.1
A81: Letno vplačilo | C81: =PMT($L$3,C77,,-C80,1) -> 25741.406 | D81: =PMT($L$3,D77,,-D80,1) -> 45454.918 | E81: =PMT($L$3,E77,,-E80,1) -> 16153.726 | F81: =PMT($L$3,F77,,-F80,1) -> 10660.726

Sheet Nadomestilo občini in voda
A1: Nadomestilo za omejeno rabo prostora in vodno povračilo [EUR/leto od začetka gradnje]
A2: 1000 MW | B2: =9953000 -> 9953000 | C2: 10441000
A3: 1250 MW | B3: =12910000 -> 12910000 | C3: 13562000
A4: 1650 MW | B4: =17641000 -> 17641000 | C4: 18556000

Sheet NPP accident insurance premium
A1: Zavarovalna premija za primer jedrske nesreče [EUR/MWh] | B1: 0 | C1: VKLJUČEVA V OPEX-U, ZATO TUKAJ 0

Sheet Tveganja
A1: Verjetnost za politično zaprtje v času gradnje JE [%] | B1: 0.005
A2: Verjetnost za politično zaprtje v času obratovanja JE [%] | B2: 0.02
A3: Verjetnost za zaprtje JE zaradi tehnične napake [%] | B3: 0.017

Sheet Ostale postavke
A1: Davek od dohodkov pravnih oseb (DDPO) | B1: 0.19

Sheet Cena elektrike
A1: Normalna porazdelitev - tuja (desno) in GEN Energija študija | B1: Pogostnost pojavljanja [%] | C1: Mean | D1: Standardna deviacija
A2: Scenarij nizka cena | B2: 0.2 | C2: 59.5 | D2: =$B$5*C2 -> 7.5084553
A3: Scenarij srednja cena | B3: 0.6 | C3: 68 | D3: =$B$5*C3 -> 8.5810918
A4: Scenarij visoka cena | B4: 0.2 | C4: 96.5 | D4: =$B$5*C4 -> 12.177579 | E4: Cene vzete iz grafa ob pomoči ekstrakcije podatkov iz grafa
A5: Standardna deviacija stran od srednje vrednosti [% od srednje vrednosti] | B5: 0.12619253 | D5: =C4+3*D4 -> 133.03274
A6: Real escalation rate [%] | B6: 0
A7: Zbrali nemške mesečne futurse, ki so 120 EUR/MWh ali višji, saj je 2SD od scenarija z visoko ceno 121 EUR/MWh meja | C7: študija
A8: Možnost, da se zgodi izjemen skok v cenah [%] | B8: =1/15 -> 0.066666667 | C8: prilagojena vrednost iz eurostata
A9: Triangularna porazdelitev
A10: Višina realnih cen, če do skoka pride - min [EUR/MWh] | B10: 133.05623
A11: Višina realnih cen, če do skoka pride - mean [EUR/MWh] | B11: 233.4634
A12: Višina realnih cen, če do skoka pride - max [EUR/MWh] | B12: 465.18

Sheet Potrdila o izvoru
A1: Potrdilo o izvoru - prihodek [EUR/MWh] | B1: 1
